Workbook

Sheet Cover
A1: ASPSI–DOH UHC CAPI — UAT Ticket Register
A2: GitHub issue export by UAT round, instrument, and resolution
A4: Prepared for | B4: ASPSI (for DOH documentation)
A5: Prepared by | B5: Carl Patrick L. Reyes — Data Programmer
A6: Generated | B6: 2026-06-29
A7: Source | B7: GitHub — cplreyes/ASPSI-DOH-UHC-CAPI-Development (Issues)
A8: Total issues in repo | B8: 736
A9: UAT-round tickets | B9: 381
A10: Non-round (dev/backlog) | B10: 355
A11: Current open issues | B11: 0
A13: UAT round legend
A14: R1 / R2 / R3 | B14: F2 PWA (Healthcare-Worker self-administered) — labels round:1 / round:2(+from-uat-round-2) / round:3(+from-uat-round-3)
A15: R4 | B15: CAPI F1/F3/F4 (interviewer-administered) — label from-uat-round-4-capi-2026-06
A16: R5 | B16: CAPI F1/F3/F4 — label from-uat-round-5-2026-06
A18: Status legend
A19: Fixed | B19: Issue resolved / fix built + deployed (GitHub: closed as completed).
A20: Deferred | B20: Closed as not-planned: duplicate, cosmetic, design decision, or parked for ASPSI input.
A21: Reported via = UAT form | B21: Filed through the GitHub UAT feedback template (label uat-feedback). 'Direct' = logged during triage. NOTE: the form label was applied mainly in R4, so this flag UNDERCOUNTS tester findings in R1-R3 / R5 — every round-tagged ticket is a UAT-round finding regardless of this flag.
A23: Notes
A24: • All issues are currently closed (0 open). Lifecycle: Raised (created date) -> Triaged + fixed -> Closed (closed date).
A25: • 'Deferred' tickets do not indicate failure — most are cosmetic, duplicate, or ASPSI-owned (translations / spec decisions) tracked separately.
A26: • A closed ticket can reopen on a stale-build desk-test failure (remove + re-add the CSEntry app to refresh).
A27: • Authoritative per-round narrative: see deliverables/CSPro/CAPI-UAT-Round-5-Closeout-2026-06-29.md and the scrum sprint records.

Sheet Summary by Round
A1: UAT Summary — tickets by round
A2: Counts are live formulas over the 'UAT Tickets' sheet (COUNTIF / COUNTIFS).
A4: Round | B4: Phase | C4: Window (raised → closed) | D4: Tickets raised | E4: Fixed | F4: Deferred | G4: Via UAT form | H4: F1 | I4: F3 | J4: F4 | K4: F2 PWA | L4: F2 Admin | M4: CSWeb
A5: R1 | B5: F2 PWA (HCW self-admin) | C5: 2026-04-23 -> 2026-04-25 | D5: =COUNTIF('UAT Tickets'!$A:$A,A5) -> 11 | E5: =COUNTIFS('UAT Tickets'!$A:$A,A5,'UAT Tickets'!$L:$L,"Fixed") -> 11 | F5: =COUNTIFS('UAT Tickets'!$A:$A,A5,'UAT Tickets'!$L:$L,"Deferred") -> 0 | G5: =COUNTIFS('UAT Tickets'!$A:$A,A5,'UAT Tickets'!$I:$I,"UAT form") -> 0 | H5: =COUNTIFS('UAT Tickets'!$A:$A,A5,'UAT Tickets'!$C:$C,"F1 — Facility Head") -> 0 | I5: =COUNTIFS('UAT Tickets'!$A:$A,A5,'UAT Tickets'!$C:$C,"F3 — Patient") -> 0 | J5: =COUNTIFS('UAT Tickets'!$A:$A,A5,'UAT Tickets'!$C:$C,"F4 — Household") -> 0 | K5: =COUNTIFS('UAT Tickets'!$A:$A,A5,'UAT Tickets'!$C:$C,"F2 — HCW (PWA)") -> 11 | L5: =COUNTIFS('UAT Tickets'!$A:$A,A5,'UAT Tickets'!$C:$C,"F2 Admin Portal") -> 0 | M5: =COUNTIFS('UAT Tickets'!$A:$A,A5,'UAT Tickets'!$C:$C,"CSWeb") -> 0
A6: R2 | B6: F2 PWA (HCW self-admin) | C6: 2026-04-25 -> 2026-05-09 | D6: =COUNTIF('UAT Tickets'!$A:$A,A6) -> 52 | E6: =COUNTIFS('UAT Tickets'!$A:$A,A6,'UAT Tickets'!$L:$L,"Fixed") -> 50 | F6: =COUNTIFS('UAT Tickets'!$A:$A,A6,'UAT Tickets'!$L:$L,"Deferred") -> 2 | G6: =COUNTIFS('UAT Tickets'!$A:$A,A6,'UAT Tickets'!$I:$I,"UAT form") -> 0 | H6: =COUNTIFS('UAT Tickets'!$A:$A,A6,'UAT Tickets'!$C:$C,"F1 — Facility Head") -> 0 | I6: =COUNTIFS('UAT Tickets'!$A:$A,A6,'UAT Tickets'!$C:$C,"F3 — Patient") -> 0 | J6: =COUNTIFS('UAT Tickets'!$A:$A,A6,'UAT Tickets'!$C:$C,"F4 — Household") -> 0 | K6: =COUNTIFS('UAT Tickets'!$A:$A,A6,'UAT Tickets'!$C:$C,"F2 — HCW (PWA)") -> 19 | L6: =COUNTIFS('UAT Tickets'!$A:$A,A6,'UAT Tickets'!$C:$C,"F2 Admin Portal") -> 33 | M6: =COUNTIFS('UAT Tickets'!$A:$A,A6,'UAT Tickets'!$C:$C,"CSWeb") -> 0
A7: R3 | B7: F2 PWA (HCW self-admin) | C7: 2026-04-25 -> 2026-06-05 | D7: =COUNTIF('UAT Tickets'!$A:$A,A7) -> 35 | E7: =COUNTIFS('UAT Tickets'!$A:$A,A7,'UAT Tickets'!$L:$L,"Fixed") -> 33 | F7: =COUNTIFS('UAT Tickets'!$A:$A,A7,'UAT Tickets'!$L:$L,"Deferred") -> 2 | G7: =COUNTIFS('UAT Tickets'!$A:$A,A7,'UAT Tickets'!$I:$I,"UAT form") -> 0 | H7: =COUNTIFS('UAT Tickets'!$A:$A,A7,'UAT Tickets'!$C:$C,"F1 — Facility Head") -> 0 | I7: =COUNTIFS('UAT Tickets'!$A:$A,A7,'UAT Tickets'!$C:$C,"F3 — Patient") -> 0 | J7: =COUNTIFS('UAT Tickets'!$A:$A,A7,'UAT Tickets'!$C:$C,"F4 — Household") -> 0 | K7: =COUNTIFS('UAT Tickets'!$A:$A,A7,'UAT Tickets'!$C:$C,"F2 — HCW (PWA)") -> 35 | L7: =COUNTIFS('UAT Tickets'!$A:$A,A7,'UAT Tickets'!$C:$C,"F2 Admin Portal") -> 0 | M7: =COUNTIFS('UAT Tickets'!$A:$A,A7,'UAT Tickets'!$C:$C,"CSWeb") -> 0
A8: R4 | B8: CAPI (F1/F3/F4 interviewer) | C8: 2026-06-12 -> 2026-06-21 | D8: =COUNTIF('UAT Tickets'!$A:$A,A8) -> 204 | E8: =COUNTIFS('UAT Tickets'!$A:$A,A8,'UAT Tickets'!$L:$L,"Fixed") -> 199 | F8: =COUNTIFS('UAT Tickets'!$A:$A,A8,'UAT Tickets'!$L:$L,"Deferred") -> 5 | G8: =COUNTIFS('UAT Tickets'!$A:$A,A8,'UAT Tickets'!$I:$I,"UAT form") -> 96 | H8: =COUNTIFS('UAT Tickets'!$A:$A,A8,'UAT Tickets'!$C:$C,"F1 — Facility Head") -> 28 | I8: =COUNTIFS('UAT Tickets'!$A:$A,A8,'UAT Tickets'!$C:$C,"F3 — Patient") -> 38 | J8: =COUNTIFS('UAT Tickets'!$A:$A,A8,'UAT Tickets'!$C:$C,"F4 — Household") -> 93 | K8: =COUNTIFS('UAT Tickets'!$A:$A,A8,'UAT Tickets'!$C:$C,"F2 — HCW (PWA)") -> 0 | L8: =COUNTIFS('UAT Tickets'!$A:$A,A8,'UAT Tickets'!$C:$C,"F2 Admin Portal") -> 0 | M8: =COUNTIFS('UAT Tickets'!$A:$A,A8,'UAT Tickets'!$C:$C,"CSWeb") -> 0
A9: R5 | B9: CAPI (F1/F3/F4 interviewer) | C9: 2026-06-21 -> 2026-06-27 | D9: =COUNTIF('UAT Tickets'!$A:$A,A9) -> 79 | E9: =COUNTIFS('UAT Tickets'!$A:$A,A9,'UAT Tickets'!$L:$L,"Fixed") -> 78 | F9: =COUNTIFS('UAT Tickets'!$A:$A,A9,'UAT Tickets'!$L:$L,"Deferred") -> 1 | G9: =COUNTIFS('UAT Tickets'!$A:$A,A9,'UAT Tickets'!$I:$I,"UAT form") -> 4 | H9: =COUNTIFS('UAT Tickets'!$A:$A,A9,'UAT Tickets'!$C:$C,"F1 — Facility Head") -> 5 | I9: =COUNTIFS('UAT Tickets'!$A:$A,A9,'UAT Tickets'!$C:$C,"F3 — Patient") -> 39 | J9: =COUNTIFS('UAT Tickets'!$A:$A,A9,'UAT Tickets'!$C:$C,"F4 — Household") -> 27 | K9: =COUNTIFS('UAT Tickets'!$A:$A,A9,'UAT Tickets'!$C:$C,"F2 — HCW (PWA)") -> 2 | L9: =COUNTIFS('UAT Tickets'!$A:$A,A9,'UAT Tickets'!$C:$C,"F2 Admin Portal") -> 0 | M9: =COUNTIFS('UAT Tickets'!$A:$A,A9,'UAT Tickets'!$C:$C,"CSWeb") -> 0
A10: TOTAL | B10: all UAT rounds | D10: =SUM(D5:D9) -> 381 | E10: =SUM(E5:E9) -> 371 | F10: =SUM(F5:F9) -> 10 | G10: =SUM(G5:G9) -> 100 | H10: =SUM(H5:H9) -> 33 | I10: =SUM(I5:I9) -> 77 | J10: =SUM(J5:J9) -> 120 | K10: =SUM(K5:K9) -> 67 | ... M10: =SUM(M5:M9) -> 0

Sheet UAT Tickets
A1: UAT Tickets — raised, triaged, fixed (by round)
A3: Round | B3: Phase | C3: Instrument | D3: Issue # | E3: Title | F3: Type | G3: Sub-type | H3: Severity | I3: Reported via | J3: Raised | K3: Closed | L3: Resolution | M3: Disposition / note | N3: Link
A4: R1 | B4: F2 PWA (HCW self-admin) | C4: F2 — HCW (PWA) | D4: 1 | E4: How old are you as of your last birthday (in years)? | F4: Other | G4: validation | H4: Medium | I4: Direct | J4: 46135 | K4: 46137 | L4: Fixed | M4: Fixed (was pending tester verify at close) | N4: https://github.com/cplreyes/ASPSI-DOH-UHC-CAPI-Development/issues/1
A5: R1 | B5: F2 PWA (HCW self-admin) | C5: F2 — HCW (PWA) | D5: 2 | E5: What is your role at this health facility? | F5: Other | G5: ux | H5: Medium | I5: Direct | J5: 46135 | K5: 46137 | L5: Fixed | M5: Fixed (was pending tester verify at close) | N5: https://github.com/cplreyes/ASPSI-DOH-UHC-CAPI-Development/issues/2
A6: R1 | B6: F2 PWA (HCW self-admin) | C6: F2 — HCW (PWA) | D6: 3 | E6: In your current position, how many (months/years) have you worked at this health facility? | F6: Other | G6: validation | H6: Medium | I6: Direct | J6: 46135 | K6: 46137 | L6: Fixed | M6: Fixed (was pending tester verify at close) | N6: https://github.com/cplreyes/ASPSI-DOH-UHC-CAPI-Development/issues/3
A7: R1 | B7: F2 PWA (HCW self-admin) | C7: F2 — HCW (PWA) | D7: 4 | E7: How old are you as of your last birthday (in years)? | F7: Other | G7: validation | H7: Medium | I7: Direct | J7: 46135 | K7: 46137 | L7: Fixed | M7: Fixed (was pending tester verify at close) | N7: https://github.com/cplreyes/ASPSI-DOH-UHC-CAPI-Development/issues/4
A8: R1 | B8: F2 PWA (HCW self-admin) | C8: F2 — HCW (PWA) | D8: 5 | E8: In your current position, how many (months/years) have you worked at this health facility? | F8: Other | G8: validation | H8: Medium | I8: Direct | J8: 46135 | K8: 46137 | L8: Fixed | M8: Fixed (was pending tester verify at close) | N8: https://github.com/cplreyes/ASPSI-DOH-UHC-CAPI-Development/issues/5
A9: R1 | B9: F2 PWA (HCW self-admin) | C9: F2 — HCW (PWA) | D9: 6 | E9: Q12.Have you heard about Universal Health Care (UHC) prior to this survey? | F9: Other | G9: skip-logic | H9: High | I9: Direct | J9: 46135 | K9: 46137 | L9: Fixed | M9: Fixed (was pending tester verify at close) | N9: https://github.com/cplreyes/ASPSI-DOH-UHC-CAPI-Development/issues/6
A10: R1 | B10: F2 PWA (HCW self-admin) | C10: F2 — HCW (PWA) | D10: 8 | E10: Q25 – Conditional Logic Restriction Issue | F10: Other | G10: skip-logic | H10: High | I10: Direct | J10: 46136 | K10: 46137 | L10: Fixed | M10: Fixed (was pending tester verify at close) | N10: https://github.com/cplreyes/ASPSI-DOH-UHC-CAPI-Development/issues/8
A11: R1 | B11: F2 PWA (HCW self-admin) | C11: F2 — HCW (PWA) | D11: 10 | E11: Auto-Advance Issue on Required Questions | F11: Bug | H11: Critical | I11: Direct | J11: 46136 | K11: 46137 | L11: Fixed | M11: Fixed (was pending tester verify at close) | N11: https://github.com/cplreyes/ASPSI-DOH-UHC-CAPI-Development/issues/10
A12: R1 | B12: F2 PWA (HCW self-admin) | C12: F2 — HCW (PWA) | D12: 11 | E12: Section Applicability Issue (Section G) | F12: Other | G12: skip-logic | H12: High | I12: Direct | J12: 46136 | K12: 46137 | L12: Fixed | M12: Fixed (was pending tester verify at close) | N12: https://github.com/cplreyes/ASPSI-DOH-UHC-CAPI-Development/issues/11
A13: R1 | B13: F2 PWA (HCW self-admin) | C13: F2 — HCW (PWA) | D13: 12 | E13: Test Scenario Observations | F13: Other | G13: sync | H13: High | I13: Direct | J13: 46136 | K13: 46137 | L13: Fixed | M13: Fixed (was pending tester verify at close) | N13: https://github.com/cplreyes/ASPSI-DOH-UHC-CAPI-Development/issues/12
A14: R1 | B14: F2 PWA (HCW self-admin) | C14: F2 — HCW (PWA) | D14: 13 | E14: Mid-section skip logic — conditional jumps not enforced (Q34/Q38/Q39/Q44/Q48/Q53/Q69/Q70/Q87/Q88) | F14: Other | G14: skip-logic | H14: High | I14: Direct | J14: 46137 | K14: 46137 | L14: Fixed | M14: Fixed (was pending tester verify at close) | N14: https://github.com/cplreyes/ASPSI-DOH-UHC-CAPI-Development/issues/13
A15: R2 | B15: F2 PWA (HCW self-admin) | C15: F2 — HCW (PWA) | D15: 14 | E15: Q9 Month(s) field should be optional, not required | F15: Other | G15: validation | H15: Medium | I15: Direct | J15: 46137 | K15: 46137 | L15: Fixed | M15: Fixed (was pending tester verify at close) | N15: https://github.com/cplreyes/ASPSI-DOH-UHC-CAPI-Development/issues/14
A16: R2 | B16: F2 PWA (HCW self-admin) | C16: F2 — HCW (PWA) | D16: 15 | E16: Cannot proceed when gating question answered No (Q12, Q31, similar) | F16: Other | G16: skip-logic | H16: Critical | I16: Direct | J16: 46137 | K16: 46137 | L16: Fixed | M16: Fixed (was pending tester verify at close) | N16: https://github.com/cplreyes/ASPSI-DOH-UHC-CAPI-Development/issues/15
A17: R2 | B17: F2 PWA (HCW self-admin) | C17: F2 — HCW (PWA) | D17: 16 | E17: I don't know option should be exclusive in multi-select questions | F17: Other | G17: ux | H17: Medium | I17: Direct | J17: 46137 | K17: 46143 | L17: Fixed | M17: Fixed (was pending tester verify at close) | N17: https://github.com/cplreyes/ASPSI-DOH-UHC-CAPI-Development/issues/16
A18: R2 | B18: F2 PWA (HCW self-admin) | C18: F2 — HCW (PWA) | D18: 17 | E18: All of the above should auto-select all other options | F18: Other | G18: ux | H18: Medium | I18: Direct | J18: 46137 | K18: 46143 | L18: Fixed | M18: Fixed (was pending tester verify at close) | N18: https://github.com/cplreyes/ASPSI-DOH-UHC-CAPI-Development/issues/17
A19: R2 | B19: F2 PWA (HCW self-admin) | C19: F2 — HCW (PWA) | D19: 18 | E19: Render scale-style questions as a 2-way matrix instead of one-by-one | F19: Enhancement | G19: ux | H19: Low | I19: Direct | J19: 46137 | K19: 46143 | L19: Fixed | M19: Fixed (was pending tester verify at close) | N19: https://github.com/cplreyes/ASPSI-DOH-UHC-CAPI-Development/issues/18
A20: R2 | B20: F2 PWA (HCW self-admin) | C20: F2 — HCW (PWA) | D20: 108 | E20: (A.1.E2) 5.1 Token-paste enrollment | F20: Bug | G20: ux | H20: Low | I20: Direct | J20: 46149 | K20: 46151 | L20: Fixed | N20: https://github.com/cplreyes/ASPSI-DOH-UHC-CAPI-Development/issues/108
A21: R2 | B21: F2 PWA (HCW self-admin) | C21: F2 — HCW (PWA) | D21: 109 | E21: (A.1.E3) 5.1 Token-paste enrollment | F21: Bug | G21: sync | H21: Low | I21: Direct | J21: 46149 | K21: 46151 | L21: Fixed | N21: https://github.com/cplreyes/ASPSI-DOH-UHC-CAPI-Development/issues/109
A22: R2 | B22: F2 PWA (HCW self-admin) | C22: F2 — HCW (PWA) | D22: 110 | E22: (A.2.E8) Q9 - 5.2 Section A — Healthcare Worker Profile (Q1–Q11) | F22: Bug | G22: validation | H22: Medium | I22: Direct | J22: 46149 | K22: 46151 | L22: Fixed | N22: https://github.com/cplreyes/ASPSI-DOH-UHC-CAPI-Development/issues/110
A23: R2 | B23: F2 PWA (HCW self-admin) | C23: F2 — HCW (PWA) | D23: 111 | E23: (B.E1) 5.3 Section B — UHC Awareness (Q25) | F23: Other | I23: Direct | J23: 46149 | K23: 46150 | L23: Fixed | N23: https://github.com/cplreyes/ASPSI-DOH-UHC-CAPI-Development/issues/111
A24: R2 | B24: F2 PWA (HCW self-admin) | C24: F2 — HCW (PWA) | D24: 112 | E24: 5. (B.E2) 5.3 Section B — UHC Awareness (Q25) | F24: Other | G24: validation | H24: High | I24: Direct | J24: 46149 | K24: 46151 | L24: Fixed | N24: https://github.com/cplreyes/ASPSI-DOH-UHC-CAPI-Development/issues/112
A25: R2 | B25: F2 PWA (HCW self-admin) | C25: F2 — HCW (PWA) | D25: 114 | E25: (C.E1) 5.4 Section C — YAKAP/Konsulta (Q31–Q40, role-gated) | F25: Bug | G25: skip-logic | H25: Critical | I25: Direct | J25: 46150 | K25: 46151 | L25: Fixed | N25: https://github.com/cplreyes/ASPSI-DOH-UHC-CAPI-Development/issues/114
A26: R2 | B26: F2 PWA (HCW self-admin) | C26: F2 — HCW (PWA) | D26: 115 | E26: (C.E2) 5.4 Section C — YAKAP/Konsulta (Q31–Q40, role-gated) | F26: Bug | G26: skip-logic | H26: Medium | I26: Direct | J26: 46150 | K26: 46151 | L26: Fixed | N26: https://github.com/cplreyes/ASPSI-DOH-UHC-CAPI-Development/issues/115
A27: R2 | B27: F2 PWA (HCW self-admin) | C27: F2 — HCW (PWA) | D27: 116 | E27: (Q44) 5.5 Section D — NBB/ZBB Awareness (Q41–Q47, role-gated) | F27: Bug | G27: skip-logic | H27: High | I27: Direct | J27: 46150 | K27: 46151 | L27: Fixed | N27: https://github.com/cplreyes/ASPSI-DOH-UHC-CAPI-Development/issues/116
A28: R2 | B28: F2 PWA (HCW self-admin) | C28: F2 — HCW (PWA) | D28: 117 | E28: Section E1 and E2 | F28: Enhancement | G28: skip-logic | I28: Direct | J28: 46150 | K28: 46151 | L28: Fixed | N28: https://github.com/cplreyes/ASPSI-DOH-UHC-CAPI-Development/issues/117
A29: R2 | B29: F2 PWA (HCW self-admin) | C29: F2 — HCW (PWA) | D29: 118 | E29: Section G — back-nav loses answers at Q87/Q88 + X icon despite ✓ + redirect to F (KAP on Professional Setting, Charging, And Reimbursement) | F29: Bug | G29: skip-logic | H29: Critical | I29: Direct | J29: 46150 | K29: 46151 | L29: Fixed | N29: https://github.com/cplreyes/ASPSI-DOH-UHC-CAPI-Development/issues/118
A30: R2 | B30: F2 PWA (HCW self-admin) | C30: F2 — HCW (PWA) | D30: 119 | E30: 5.12 Section J — Job Satisfaction (Q98–Q125, two matrix grids + terminal branch) | F30: Bug | G30: skip-logic | H30: Critical | I30: Direct | J30: 46150 | K30: 46151 | L30: Fixed | N30: https://github.com/cplreyes/ASPSI-DOH-UHC-CAPI-Development/issues/119
A31: R2 | B31: F2 PWA (HCW self-admin) | C31: F2 — HCW (PWA) | D31: 120 | E31: 5.13 Submission + Sync | F31: Bug | G31: sync | H31: Medium | I31: Direct | J31: 46150 | K31: 46151 | L31: Fixed | N31: https://github.com/cplreyes/ASPSI-DOH-UHC-CAPI-Development/issues/120
A32: R2 | B32: F2 PWA (HCW self-admin) | C32: F2 — HCW (PWA) | D32: 121 | E32: Sync/Submission | F32: Bug | G32: sync | H32: Medium | I32: Direct | J32: 46150 | K32: 46151 | L32: Fixed | N32: https://github.com/cplreyes/ASPSI-DOH-UHC-CAPI-Development/issues/121
A33: R2 | B33: F2 PWA (HCW self-admin) | C33: F2 — HCW (PWA) | D33: 122 | E33: Sync + Submission | F33: Bug | G33: sync | H33: Critical | I33: Direct | J33: 46150 | K33: 46151 | L33: Fixed | N33: https://github.com/cplreyes/ASPSI-DOH-UHC-CAPI-Development/issues/122
A34: R2 | B34: F2 PWA (HCW self-admin) | C34: F2 Admin Portal | D34: 68 | E34: #4 – Reference: Admin Portal Layout | F34: Bug | H34: High | I34: Direct | J34: 46149 | K34: 46151 | L34: Fixed | M34: Fixed (was pending tester verify at close) | N34: https://github.com/cplreyes/ASPSI-DOH-UHC-CAPI-Development/issues/68
A35: R2 | B35: F2 PWA (HCW self-admin) | C35: F2 Admin Portal | D35: 69 | E35: 5.1 Login + session | F35: Bug | G35: ux | H35: Low | I35: Direct | J35: 46149 | K35: 46151 | L35: Fixed | M35: Fixed (was pending tester verify at close) | N35: https://github.com/cplreyes/ASPSI-DOH-UHC-CAPI-Development/issues/69
A36: R2 | B36: F2 PWA (HCW self-admin) | C36: F2 Admin Portal | D36: 70 | E36: Login + session | F36: Bug | I36: Direct | J36: 46149 | K36: 46151 | L36: Fixed | M36: Fixed (was pending tester verify at close) | N36: https://github.com/cplreyes/ASPSI-DOH-UHC-CAPI-Development/issues/70
A37: R2 | B37: F2 PWA (HCW self-admin) | C37: F2 Admin Portal | D37: 71 | E37: Login + session | F37: Bug | I37: Direct | J37: 46149 | K37: 46151 | L37: Fixed | M37: Fixed (was pending tester verify at close) | N37: https://github.com/cplreyes/ASPSI-DOH-UHC-CAPI-Development/issues/71
A38: R2 | B38: F2 PWA (HCW self-admin) | C38: F2 Admin Portal | D38: 72 | E38: Login + session | F38: Bug | I38: Direct | J38: 46149 | K38: 46151 | L38: Fixed | M38: Fixed (was pending tester verify at close) | N38: https://github.com/cplreyes/ASPSI-DOH-UHC-CAPI-Development/issues/72
A39: R2 | B39: F2 PWA (HCW self-admin) | C39: F2 Admin Portal | D39: 78 | E39: Data dashboard — Responses sub-tab - Other Observation | F39: Bug | I39: Direct | J39: 46149 | K39: 46151 | L39: Fixed | M39: Fixed (was pending tester verify at close) | N39: https://github.com/cplreyes/ASPSI-DOH-UHC-CAPI-Development/issues/78
A40: R2 | B40: F2 PWA (HCW self-admin) | C40: F2 Admin Portal | D40: 79 | E40: 5.3 Data dashboard — Audit sub-tab | F40: Bug | I40: Direct | J40: 46149 | K40: 46151 | L40: Fixed | M40: Fixed (was pending tester verify at close) | N40: https://github.com/cplreyes/ASPSI-DOH-UHC-CAPI-Development/issues/79
A41: R2 | B41: F2 PWA (HCW self-admin) | C41: F2 Admin Portal | D41: 80 | E41: Data dashboard — Audit sub-tab | F41: Bug | I41: Direct | J41: 46149 | K41: 46151 | L41: Fixed | M41: Fixed (was pending tester verify at close) | N41: https://github.com/cplreyes/ASPSI-DOH-UHC-CAPI-Development/issues/80
A42: R2 | B42: F2 PWA (HCW self-admin) | C42: F2 Admin Portal | D42: 82 | E42: Data dashboard — Audit sub-tab - Other Observations | F42: Bug | I42: Direct | J42: 46149 | K42: 46151 | L42: Fixed | M42: Fixed (was pending tester verify at close) | N42: https://github.com/cplreyes/ASPSI-DOH-UHC-CAPI-Development/issues/82
A43: R2 | B43: F2 PWA (HCW self-admin) | C43: F2 Admin Portal | D43: 83 | E43: Data dashboard — DLQ sub-tab | F43: Bug | I43: Direct | J43: 46149 | K43: 46151 | L43: Fixed | M43: Fixed (was pending tester verify at close) | N43: https://github.com/cplreyes/ASPSI-DOH-UHC-CAPI-Development/issues/83
A44: R2 | B44: F2 PWA (HCW self-admin) | C44: F2 Admin Portal | D44: 84 | E44: Data dashboard — DLQ sub-tab | F44: Bug | H44: Medium | I44: Direct | J44: 46149 | K44: 46151 | L44: Fixed | M44: Fixed (was pending tester verify at close) | N44: https://github.com/cplreyes/ASPSI-DOH-UHC-CAPI-Development/issues/84
A45: R2 | B45: F2 PWA (HCW self-admin) | C45: F2 Admin Portal | D45: 85 | E45: 5.5 Data dashboard — HCWs sub-tab + Reissue Token flow | F45: Bug | I45: Direct | J45: 46149 | K45: 46151 | L45: Fixed | M45: Fixed (was pending tester verify at close) | N45: https://github.com/cplreyes/ASPSI-DOH-UHC-CAPI-Development/issues/85
A46: R2 | B46: F2 PWA (HCW self-admin) | C46: F2 Admin Portal | D46: 86 | E46: Data dashboard — HCWs sub-tab + Reissue Token flow | F46: Bug | I46: Direct | J46: 46149 | K46: 46151 | L46: Fixed | M46: Fixed (was pending tester verify at close) | N46: https://github.com/cplreyes/ASPSI-DOH-UHC-CAPI-Development/issues/86
A47: R2 | B47: F2 PWA (HCW self-admin) | C47: F2 Admin Portal | D47: 87 | E47: Data dashboard — HCWs sub-tab + Reissue Token flow | F47: Bug | I47: Direct | J47: 46149 | K47: 46151 | L47: Fixed | M47: Fixed (was pending tester verify at close) | N47: https://github.com/cplreyes/ASPSI-DOH-UHC-CAPI-Development/issues/87
A48: R2 | B48: F2 PWA (HCW self-admin) | C48: F2 Admin Portal | D48: 88 | E48: Data dashboard — HCWs sub-tab + Reissue Token flow | F48: Bug | I48: Direct | J48: 46149 | K48: 46151 | L48: Fixed | M48: Fixed (was pending tester verify at close) | N48: https://github.com/cplreyes/ASPSI-DOH-UHC-CAPI-Development/issues/88
A49: R2 | B49: F2 PWA (HCW self-admin) | C49: F2 Admin Portal | D49: 89 | E49: 5.7 Reports — Map Report sub-tab | F49: Bug | H49: High | I49: Direct | J49: 46149 | K49: 46151 | L49: Fixed | M49: Fixed (was pending tester verify at close) | N49: https://github.com/cplreyes/ASPSI-DOH-UHC-CAPI-Development/issues/89
A50: R2 | B50: F2 PWA (HCW self-admin) | C50: F2 Admin Portal | D50: 90 | E50: Reports — Map Report sub-tab | F50: Bug | H50: High | I50: Direct | J50: 46149 | K50: 46151 | L50: Fixed | N50: https://github.com/cplreyes/ASPSI-DOH-UHC-CAPI-Development/issues/90
A51: R2 | B51: F2 PWA (HCW self-admin) | C51: F2 Admin Portal | D51: 91 | E51: 5.9 Apps & Settings — Files sub-tab | F51: Bug | I51: Direct | J51: 46149 | K51: 46151 | L51: Fixed | N51: https://github.com/cplreyes/ASPSI-DOH-UHC-CAPI-Development/issues/91
A52: R2 | B52: F2 PWA (HCW self-admin) | C52: F2 Admin Portal | D52: 92 | E52: Apps & Settings — Files sub-tab | F52: Bug | I52: Direct | J52: 46149 | K52: 46151 | L52: Fixed | N52: https://github.com/cplreyes/ASPSI-DOH-UHC-CAPI-Development/issues/92
A53: R2 | B53: F2 PWA (HCW self-admin) | C53: F2 Admin Portal | D53: 93 | E53: Apps & Settings — Files sub-tab | F53: Bug | G53: i18n | H53: Medium | I53: Direct | J53: 46149 | K53: 46151 | L53: Fixed | N53: https://github.com/cplreyes/ASPSI-DOH-UHC-CAPI-Development/issues/93
A54: R2 | B54: F2 PWA (HCW self-admin) | C54: F2 Admin Portal | D54: 94 | E54: 5.10 Apps & Settings — Data Settings sub-tab | F54: Bug | I54: Direct | J54: 46149 | K54: 46151 | L54: Fixed | N54: https://github.com/cplreyes/ASPSI-DOH-UHC-CAPI-Development/issues/94
A55: R2 | B55: F2 PWA (HCW self-admin) | C55: F2 Admin Portal | D55: 95 | E55: Apps & Settings — Data Settings sub-tab | F55: Bug | I55: Direct | J55: 46149 | K55: 46151 | L55: Fixed | N55: https://github.com/cplreyes/ASPSI-DOH-UHC-CAPI-Development/issues/95
A56: R2 | B56: F2 PWA (HCW self-admin) | C56: F2 Admin Portal | D56: 96 | E56: Apps & Settings — Data Settings sub-tab | F56: Bug | I56: Direct | J56: 46149 | K56: 46151 | L56: Fixed | N56: https://github.com/cplreyes/ASPSI-DOH-UHC-CAPI-Development/issues/96
A57: R2 | B57: F2 PWA (HCW self-admin) | C57: F2 Admin Portal | D57: 97 | E57: 5.11 Apps & Settings — Apps Script Quota sub-tab | F57: Bug | I57: Direct | J57: 46149 | K57: 46151 | L57: Fixed | N57: https://github.com/cplreyes/ASPSI-DOH-UHC-CAPI-Development/issues/97
A58: R2 | B58: F2 PWA (HCW self-admin) | C58: F2 Admin Portal | D58: 98 | E58: 5.12 Users dashboard | F58: Bug | H58: Medium | I58: Direct | J58: 46149 | K58: 46151 | L58: Fixed | N58: https://github.com/cplreyes/ASPSI-DOH-UHC-CAPI-Development/issues/98
A59: R2 | B59: F2 PWA (HCW self-admin) | C59: F2 Admin Portal | D59: 99 | E59: Users dashboard | F59: Bug | I59: Direct | J59: 46149 | K59: 46151 | L59: Fixed | N59: https://github.com/cplreyes/ASPSI-DOH-UHC-CAPI-Development/issues/99
A60: R2 | B60: F2 PWA (HCW self-admin) | C60: F2 Admin Portal | D60: 100 | E60: 5.12 Users dashboard | F60: Other | H60: Low | I60: Direct | J60: 46149 | K60: 46151 | L60: Fixed | N60: https://github.com/cplreyes/ASPSI-DOH-UHC-CAPI-Development/issues/100
A61: R2 | B61: F2 PWA (HCW self-admin) | C61: F2 Admin Portal | D61: 102 | E61: 5.14 RBAC + persona switching (the spec story) | F61: Bug | G61: security | H61: High | I61: Direct | J61: 46149 | K61: 46151 | L61: Fixed | N61: https://github.com/cplreyes/ASPSI-DOH-UHC-CAPI-Development/issues/102
A62: R2 | B62: F2 PWA (HCW self-admin) | C62: F2 Admin Portal | D62: 103 | E62: RBAC + persona switching (the spec story) | F62: Bug | I62: Direct | J62: 46149 | K62: 46151 | L62: Fixed | N62: https://github.com/cplreyes/ASPSI-DOH-UHC-CAPI-Development/issues/103
A63: R2 | B63: F2 PWA (HCW self-admin) | C63: F2 Admin Portal | D63: 104 | E63: RB.E2 RBAC + persona switching (the spec story) | F63: Other | I63: Direct | J63: 46149 | K63: 46151 | L63: Fixed | N63: https://github.com/cplreyes/ASPSI-DOH-UHC-CAPI-Development/issues/104
A64: R2 | B64: F2 PWA (HCW self-admin) | C64: F2 Admin Portal | D64: 105 | E64: 5.16 Sub-tab pattern + sidebar (N.H2) | F64: Other | I64: Direct | J64: 46149 | K64: 46151 | L64: Fixed | N64: https://github.com/cplreyes/ASPSI-DOH-UHC-CAPI-Development/issues/105
A65: R2 | B65: F2 PWA (HCW self-admin) | C65: F2 Admin Portal | D65: 106 | E65: 5.17 Encode dashboard (paper-encoded path) (EH.1) | F65: Other | I65: Direct | J65: 46149 | K65: 46151 | L65: Deferred | M65: Not actioned / deferred | N65: https://github.com/cplreyes/ASPSI-DOH-UHC-CAPI-Development/issues/106
A66: R2 | B66: F2 PWA (HCW self-admin) | C66: F2 Admin Portal | D66: 107 | E66: 5.17 Encode dashboard (paper-encoded path) | F66: Other | I66: Direct | J66: 46149 | K66: 46151 | L66: Deferred | M66: Not actioned / deferred | N66: https://github.com/cplreyes/ASPSI-DOH-UHC-CAPI-Development/issues/107
A67: R3 | B67: F2 PWA (HCW self-admin) | C67: F2 — HCW (PWA) | D67: 19 | E67: Q4/Q9/Q10/Q11 — raw Zod error 'Expected number, received nan' leaks to UI | F67: Other | G67: validation | H67: High | I67: Direct | J67: 46137 | K67: 46143 | L67: Fixed | N67: https://github.com/cplreyes/ASPSI-DOH-UHC-CAPI-Development/issues/19
A68: R3 | B68: F2 PWA (HCW self-admin) | C68: F2 — HCW (PWA) | D68: 20 | E68: Inverted heading hierarchy — page H1 (18px) smaller than section H2 (24px) | F68: Other | G68: visual | H68: High | I68: Direct | J68: 46137 | K68: 46143 | L68: Fixed | N68: https://github.com/cplreyes/ASPSI-DOH-UHC-CAPI-Development/issues/20
A69: R3 | B69: F2 PWA (HCW self-admin) | C69: F2 — HCW (PWA) | D69: 21 | E69: Form layout pushed off-center on viewports ≥1600px | F69: Other | G69: visual | H69: High | I69: Direct | J69: 46137 | K69: 46143 | L69: Fixed | N69: https://github.com/cplreyes/ASPSI-DOH-UHC-CAPI-Development/issues/21
A70: R3 | B70: F2 PWA (HCW self-admin) | C70: F2 — HCW (PWA) | D70: 22 | E70: Disabled buttons fail WCAG AA contrast (opacity:0.5 on teal → ~2:1) | F70: Other | G70: visual | H70: High | I70: Direct | J70: 46137 | K70: 46143 | L70: Fixed | N70: https://github.com/cplreyes/ASPSI-DOH-UHC-CAPI-Development/issues/22
A71: R3 | B71: F2 PWA (HCW self-admin) | C71: F2 — HCW (PWA) | D71: 23 | E71: Default button height 32px below 44px tablet touch-target minimum | F71: Other | G71: ux | H71: Medium | I71: Direct | J71: 46137 | K71: 46143 | L71: Fixed | N71: https://github.com/cplreyes/ASPSI-DOH-UHC-CAPI-Development/issues/23
A72: R3 | B72: F2 PWA (HCW self-admin) | C72: F2 — HCW (PWA) | D72: 24 | E72: No visible focus ring on keyboard Tab navigation | F72: Other | G72: a11y | H72: Medium | I72: Direct | J72: 46137 | K72: 46143 | L72: Fixed | N72: https://github.com/cplreyes/ASPSI-DOH-UHC-CAPI-Development/issues/24
A73: R3 | B73: F2 PWA (HCW self-admin) | C73: F2 — HCW (PWA) | D73: 25 | E73: Q1_3 Middle Initial should be optional (apply same fix pattern as #14) | F73: Other | G73: validation | H73: Low | I73: Direct | J73: 46137 | K73: 46143 | L73: Fixed | N73: https://github.com/cplreyes/ASPSI-DOH-UHC-CAPI-Development/issues/25
A74: R3 | B74: F2 PWA (HCW self-admin) | C74: F2 — HCW (PWA) | D74: 26 | E74: Inconsistent Other label casing Q2 comma form vs Q5 parens form | F74: Other | G74: ux | H74: Low | I74: Direct | J74: 46137 | K74: 46143 | L74: Fixed | N74: https://github.com/cplreyes/ASPSI-DOH-UHC-CAPI-Development/issues/26
A75: R3 | B75: F2 PWA (HCW self-admin) | C75: F2 — HCW (PWA) | D75: 27 | E75: Locked sidebar sections appear as enabled buttons in a11y tree | F75: Other | G75: a11y | H75: Low | I75: Direct | J75: 46137 | K75: 46143 | L75: Fixed | N75: https://github.com/cplreyes/ASPSI-DOH-UHC-CAPI-Development/issues/27
A76: R3 | B76: F2 PWA (HCW self-admin) | C76: F2 — HCW (PWA) | D76: 28 | E76: Test Facility present in seed/cached facility list (also on staging) | F76: Other | G76: ux | H76: Low | I76: Direct | J76: 46137 | K76: 46143 | L76: Fixed | N76: https://github.com/cplreyes/ASPSI-DOH-UHC-CAPI-Development/issues/28
A77: R3 | B77: F2 PWA (HCW self-admin) | C77: F2 — HCW (PWA) | D77: 29 | E77: Right-edge floating arrow indicator clips off-screen at 375px viewport | F77: Other | G77: visual | H77: Low | I77: Direct | J77: 46137 | K77: 46143 | L77: Fixed | N77: https://github.com/cplreyes/ASPSI-DOH-UHC-CAPI-Development/issues/29
A78: R3 | B78: F2 PWA (HCW self-admin) | C78: F2 — HCW (PWA) | D78: 30 | E78: Header subtitle low contrast uses --muted instead of --muted-foreground | F78: Other | G78: visual | H78: Low | I78: Direct | J78: 46137 | K78: 46143 | L78: Fixed | N78: https://github.com/cplreyes/ASPSI-DOH-UHC-CAPI-Development/issues/30
A79: R3 | B79: F2 PWA (HCW self-admin) | C79: F2 — HCW (PWA) | D79: 33 | E79: Section F/G multi-select state pollution: selections unchecked when answering other questions | F79: Other | G79: ux | H79: High | I79: Direct | J79: 46138 | K79: 46142 | L79: Fixed | N79: https://github.com/cplreyes/ASPSI-DOH-UHC-CAPI-Development/issues/33
A80: R3 | B80: F2 PWA (HCW self-admin) | C80: F2 — HCW (PWA) | D80: 34 | E80: Cloudflare Pages auto-deploy on staging push is not firing | F80: Other | H80: High | I80: Direct | J80: 46138 | K80: 46142 | L80: Fixed | N80: https://github.com/cplreyes/ASPSI-DOH-UHC-CAPI-Development/issues/34
A81: R3 | B81: F2 PWA (HCW self-admin) | C81: F2 — HCW (PWA) | D81: 35 | E81: Worker PBKDF2 hash defaults (600k iters) exceed Cloudflare Workers runtime cap (100k) | F81: Other | H81: Medium | I81: Direct | J81: 46138 | K81: 46143 | L81: Fixed | N81: https://github.com/cplreyes/ASPSI-DOH-UHC-CAPI-Development/issues/35
A82: R3 | B82: F2 PWA (HCW self-admin) | C82: F2 — HCW (PWA) | D82: 45 | E82: F2 PWA `.env.local` stale — missing `VITE_F2_PROXY_URL` silently breaks staging build | F82: Other | H82: High | I82: Direct | J82: 46142 | K82: 46143 | L82: Fixed | N82: https://github.com/cplreyes/ASPSI-DOH-UHC-CAPI-Development/issues/45
A83: R3 | B83: F2 PWA (HCW self-admin) | C83: F2 — HCW (PWA) | D83: 46 | E83: F2 PWA enrollment: Enroll button no-ops on real-browser staging (verified token, no IDB write, no error) | F83: Other | H83: High | I83: Direct | J83: 46142 | K83: 46143 | L83: Fixed | N83: https://github.com/cplreyes/ASPSI-DOH-UHC-CAPI-Development/issues/46
A84: R3 | B84: F2 PWA (HCW self-admin) | C84: F2 — HCW (PWA) | D84: 52 | E84: EnrollmentScreen: Refresh button uses pre-enrollment deviceToken (empty) instead of verified token | F84: Other | G84: ux | H84: Medium | I84: Direct | J84: 46143 | K84: 46143 | L84: Fixed | N84: https://github.com/cplreyes/ASPSI-DOH-UHC-CAPI-Development/issues/52
A85: R3 | B85: F2 PWA (HCW self-admin) | C85: F2 — HCW (PWA) | D85: 271 | E85: [E6-PWA-007] UAT Round 3 — R2 + v2.0.1 regression + new-scenarios bundle (HCW survey + Admin Portal, on prod v2.0.0+v2.0.1) | F85: Other | I85: Direct | J85: 46151 | K85: 46161 | L85: Fixed | N85: https://github.com/cplreyes/ASPSI-DOH-UHC-CAPI-Development/issues/271
A86: R3 | B86: F2 PWA (HCW self-admin) | C86: F2 — HCW (PWA) | D86: 294 | E86: [P0][E4-PWA-014] AS deploy gap blocks v2.0.1 admin features (admin_users_change_password, bulk_import, etc.) | F86: Other | H86: Critical | I86: Direct | J86: 46154 | K86: 46174 | L86: Fixed | N86: https://github.com/cplreyes/ASPSI-DOH-UHC-CAPI-Development/issues/294
A87: R3 | B87: F2 PWA (HCW self-admin) | C87: F2 — HCW (PWA) | D87: 296 | E87: 5.A2 - Round 3 (R2 + v2.0.1 Fix Regression) | F87: Bug | H87: High | I87: Direct | J87: 46155 | K87: 46161 | L87: Fixed | N87: https://github.com/cplreyes/ASPSI-DOH-UHC-CAPI-Development/issues/296
A88: R3 | B88: F2 PWA (HCW self-admin) | C88: F2 — HCW (PWA) | D88: 298 | E88: Section E1/E2 issues (BUCAS / GAMOT awareness) | F88: Bug | H88: High | I88: Direct | J88: 46156 | K88: 46161 | L88: Fixed | N88: https://github.com/cplreyes/ASPSI-DOH-UHC-CAPI-Development/issues/298
A89: R3 | B89: F2 PWA (HCW self-admin) | C89: F2 — HCW (PWA) | D89: 302 | E89: [F2 PWA UAT R3] Section B Q13 to Q24: can proceed to next section even if no specification of "reasons" | F89: Bug | H89: High | I89: Direct | J89: 46157 | K89: 46161 | L89: Fixed | N89: https://github.com/cplreyes/ASPSI-DOH-UHC-CAPI-Development/issues/302
A90: R3 | B90: F2 PWA (HCW self-admin) | C90: F2 — HCW (PWA) | D90: 303 | E90: Section A Q11 - answer with decimal | F90: Design decision | H90: Medium | I90: Direct | J90: 46157 | K90: 46169 | L90: Fixed | M90: Resolved as design decision | N90: https://github.com/cplreyes/ASPSI-DOH-UHC-CAPI-Development/issues/303
A91: R3 | B91: F2 PWA (HCW self-admin) | C91: F2 — HCW (PWA) | D91: 304 | E91: Section E Q52 - option 'No significant impact' | F91: Design decision | G91: validation | H91: Medium | I91: Direct | J91: 46157 | K91: 46170 | L91: Fixed | M91: Resolved as design decision | N91: https://github.com/cplreyes/ASPSI-DOH-UHC-CAPI-Development/issues/304
A92: R3 | B92: F2 PWA (HCW self-admin) | C92: F2 — HCW (PWA) | D92: 305 | E92: Section A Q9 - constraints in answers for 'Year' and 'Months' | F92: Design decision | G92: validation | H92: Medium | I92: Direct | J92: 46157 | K92: 46177 | L92: Fixed | M92: Resolved as design decision | N92: https://github.com/cplreyes/ASPSI-DOH-UHC-CAPI-Development/issues/305
A93: R3 | B93: F2 PWA (HCW self-admin) | C93: F2 — HCW (PWA) | D93: 306 | E93: Section C Q35 - code for 'Don't Know' or 'Can't recall' | F93: Design decision | G93: ux | H93: Medium | I93: Direct | J93: 46157 | K93: 46174 | L93: Fixed | M93: Resolved as design decision | N93: https://github.com/cplreyes/ASPSI-DOH-UHC-CAPI-Development/issues/306
A94: R3 | B94: F2 PWA (HCW self-admin) | C94: F2 — HCW (PWA) | D94: 307 | E94: Section C Q36 - allows only one answer | F94: Design decision | G94: skip-logic | H94: Medium | I94: Direct | J94: 46157 | K94: 46178 | L94: Fixed | M94: Resolved as design decision | N94: https://github.com/cplreyes/ASPSI-DOH-UHC-CAPI-Development/issues/307
A95: R3 | B95: F2 PWA (HCW self-admin) | C95: F2 — HCW (PWA) | D95: 308 | E95: Section C Q38 in relation to Q34 | F95: Bug | H95: Medium | I95: Direct | J95: 46157 | K95: 46161 | L95: Fixed | N95: https://github.com/cplreyes/ASPSI-DOH-UHC-CAPI-Development/issues/308
A96: R3 | B96: F2 PWA (HCW self-admin) | C96: F2 — HCW (PWA) | D96: 309 | E96: Section C Q39 option “Not a physician/dentist” | F96: Design decision | G96: validation | H96: Medium | I96: Direct | J96: 46157 | K96: 46178 | L96: Deferred | M96: Design decision — ASPSI | N96: https://github.com/cplreyes/ASPSI-DOH-UHC-CAPI-Development/issues/309
A97: R3 | B97: F2 PWA (HCW self-admin) | C97: F2 — HCW (PWA) | D97: 310 | E97: Section D Q47 - option for "None" | F97: Design decision | G97: validation | H97: Medium | I97: Direct | J97: 46157 | K97: 46170 | L97: Fixed | M97: Resolved as design decision | N97: https://github.com/cplreyes/ASPSI-DOH-UHC-CAPI-Development/issues/310
A98: R3 | B98: F2 PWA (HCW self-admin) | C98: F2 — HCW (PWA) | D98: 311 | E98: Section J Q110 - option for "None" | F98: Design decision | G98: validation | H98: Medium | I98: Direct | J98: 46157 | K98: 46170 | L98: Fixed | M98: Resolved as design decision | N98: https://github.com/cplreyes/ASPSI-DOH-UHC-CAPI-Development/issues/311
A99: R3 | B99: F2 PWA (HCW self-admin) | C99: F2 — HCW (PWA) | D99: 312 | E99: Section J Q125 - allowing multiple responses | F99: Design decision | G99: validation | H99: Medium | I99: Direct | J99: 46157 | K99: 46178 | L99: Deferred | M99: Design decision — ASPSI | N99: https://github.com/cplreyes/ASPSI-DOH-UHC-CAPI-Development/issues/312
A100: R3 | B100: F2 PWA (HCW self-admin) | C100: F2 — HCW (PWA) | D100: 313 | E100: Putting note for the respondents: "Multiple response allowed" | F100: Bug | H100: Low | I100: Direct | J100: 46157 | K100: 46161 | L100: Fixed | N100: https://github.com/cplreyes/ASPSI-DOH-UHC-CAPI-Development/issues/313
A101: R3 | B101: F2 PWA (HCW self-admin) | C101: F2 — HCW (PWA) | D101: 314 | E101: Cannot see the responses in matrix (Job Satisfaction) when editing | F101: Bug | H101: High | I101: Direct | J101: 46157 | K101: 46162 | L101: Fixed | M101: Resolved as design decision | N101: https://github.com/cplreyes/ASPSI-DOH-UHC-CAPI-Development/issues/314
...

Sheet All Issues
A1: All GitHub issues (full register, incl. non-UAT dev/backlog)
A3: Round | B3: Phase | C3: Instrument | D3: Issue # | E3: Title | F3: Type | G3: Sub-type | H3: Severity | I3: Reported via | J3: Raised | K3: Closed | L3: Resolution | M3: Disposition / note | N3: Link
A4: R1 | B4: F2 PWA (HCW self-admin) | C4: F2 — HCW (PWA) | D4: 1 | E4: How old are you as of your last birthday (in years)? | F4: Other | G4: validation | H4: Medium | I4: Direct | J4: 46135 | K4: 46137 | L4: Fixed | M4: Fixed (was pending tester verify at close) | N4: https://github.com/cplreyes/ASPSI-DOH-UHC-CAPI-Development/issues/1
A5: R1 | B5: F2 PWA (HCW self-admin) | C5: F2 — HCW (PWA) | D5: 2 | E5: What is your role at this health facility? | F5: Other | G5: ux | H5: Medium | I5: Direct | J5: 46135 | K5: 46137 | L5: Fixed | M5: Fixed (was pending tester verify at close) | N5: https://github.com/cplreyes/ASPSI-DOH-UHC-CAPI-Development/issues/2
A6: R1 | B6: F2 PWA (HCW self-admin) | C6: F2 — HCW (PWA) | D6: 3 | E6: In your current position, how many (months/years) have you worked at this health facility? | F6: Other | G6: validation | H6: Medium | I6: Direct | J6: 46135 | K6: 46137 | L6: Fixed | M6: Fixed (was pending tester verify at close) | N6: https://github.com/cplreyes/ASPSI-DOH-UHC-CAPI-Development/issues/3
A7: R1 | B7: F2 PWA (HCW self-admin) | C7: F2 — HCW (PWA) | D7: 4 | E7: How old are you as of your last birthday (in years)? | F7: Other | G7: validation | H7: Medium | I7: Direct | J7: 46135 | K7: 46137 | L7: Fixed | M7: Fixed (was pending tester verify at close) | N7: https://github.com/cplreyes/ASPSI-DOH-UHC-CAPI-Development/issues/4
A8: R1 | B8: F2 PWA (HCW self-admin) | C8: F2 — HCW (PWA) | D8: 5 | E8: In your current position, how many (months/years) have you worked at this health facility? | F8: Other | G8: validation | H8: Medium | I8: Direct | J8: 46135 | K8: 46137 | L8: Fixed | M8: Fixed (was pending tester verify at close) | N8: https://github.com/cplreyes/ASPSI-DOH-UHC-CAPI-Development/issues/5
A9: R1 | B9: F2 PWA (HCW self-admin) | C9: F2 — HCW (PWA) | D9: 6 | E9: Q12.Have you heard about Universal Health Care (UHC) prior to this survey? | F9: Other | G9: skip-logic | H9: High | I9: Direct | J9: 46135 | K9: 46137 | L9: Fixed | M9: Fixed (was pending tester verify at close) | N9: https://github.com/cplreyes/ASPSI-DOH-UHC-CAPI-Development/issues/6
A10: (none) | C10: General / Dev | D10: 7 | E10: Q9 – Months Input Validation | F10: Duplicate | I10: Direct | J10: 46136 | K10: 46137 | L10: Deferred | M10: Duplicate | N10: https://github.com/cplreyes/ASPSI-DOH-UHC-CAPI-Development/issues/7
A11: R1 | B11: F2 PWA (HCW self-admin) | C11: F2 — HCW (PWA) | D11: 8 | E11: Q25 – Conditional Logic Restriction Issue | F11: Other | G11: skip-logic | H11: High | I11: Direct | J11: 46136 | K11: 46137 | L11: Fixed | M11: Fixed (was pending tester verify at close) | N11: https://github.com/cplreyes/ASPSI-DOH-UHC-CAPI-Development/issues/8
A12: (none) | C12: General / Dev | D12: 9 | E12: Skip Logic / Navigation Issues | F12: Duplicate | I12: Direct | J12: 46136 | K12: 46137 | L12: Deferred | M12: Duplicate | N12: https://github.com/cplreyes/ASPSI-DOH-UHC-CAPI-Development/issues/9
A13: R1 | B13: F2 PWA (HCW self-admin) | C13: F2 — HCW (PWA) | D13: 10 | E13: Auto-Advance Issue on Required Questions | F13: Bug | H13: Critical | I13: Direct | J13: 46136 | K13: 46137 | L13: Fixed | M13: Fixed (was pending tester verify at close) | N13: https://github.com/cplreyes/ASPSI-DOH-UHC-CAPI-Development/issues/10
A14: R1 | B14: F2 PWA (HCW self-admin) | C14: F2 — HCW (PWA) | D14: 11 | E14: Section Applicability Issue (Section G) | F14: Other | G14: skip-logic | H14: High | I14: Direct | J14: 46136 | K14: 46137 | L14: Fixed | M14: Fixed (was pending tester verify at close) | N14: https://github.com/cplreyes/ASPSI-DOH-UHC-CAPI-Development/issues/11
A15: R1 | B15: F2 PWA (HCW self-admin) | C15: F2 — HCW (PWA) | D15: 12 | E15: Test Scenario Observations | F15: Other | G15: sync | H15: High | I15: Direct | J15: 46136 | K15: 46137 | L15: Fixed | M15: Fixed (was pending tester verify at close) | N15: https://github.com/cplreyes/ASPSI-DOH-UHC-CAPI-Development/issues/12
A16: R1 | B16: F2 PWA (HCW self-admin) | C16: F2 — HCW (PWA) | D16: 13 | E16: Mid-section skip logic — conditional jumps not enforced (Q34/Q38/Q39/Q44/Q48/Q53/Q69/Q70/Q87/Q88) | F16: Other | G16: skip-logic | H16: High | I16: Direct | J16: 46137 | K16: 46137 | L16: Fixed | M16: Fixed (was pending tester verify at close) | N16: https://github.com/cplreyes/ASPSI-DOH-UHC-CAPI-Development/issues/13
A17: R2 | B17: F2 PWA (HCW self-admin) | C17: F2 — HCW (PWA) | D17: 14 | E17: Q9 Month(s) field should be optional, not required | F17: Other | G17: validation | H17: Medium | I17: Direct | J17: 46137 | K17: 46137 | L17: Fixed | M17: Fixed (was pending tester verify at close) | N17: https://github.com/cplreyes/ASPSI-DOH-UHC-CAPI-Development/issues/14
A18: R2 | B18: F2 PWA (HCW self-admin) | C18: F2 — HCW (PWA) | D18: 15 | E18: Cannot proceed when gating question answered No (Q12, Q31, similar) | F18: Other | G18: skip-logic | H18: Critical | I18: Direct | J18: 46137 | K18: 46137 | L18: Fixed | M18: Fixed (was pending tester verify at close) | N18: https://github.com/cplreyes/ASPSI-DOH-UHC-CAPI-Development/issues/15
A19: R2 | B19: F2 PWA (HCW self-admin) | C19: F2 — HCW (PWA) | D19: 16 | E19: I don't know option should be exclusive in multi-select questions | F19: Other | G19: ux | H19: Medium | I19: Direct | J19: 46137 | K19: 46143 | L19: Fixed | M19: Fixed (was pending tester verify at close) | N19: https://github.com/cplreyes/ASPSI-DOH-UHC-CAPI-Development/issues/16
A20: R2 | B20: F2 PWA (HCW self-admin) | C20: F2 — HCW (PWA) | D20: 17 | E20: All of the above should auto-select all other options | F20: Other | G20: ux | H20: Medium | I20: Direct | J20: 46137 | K20: 46143 | L20: Fixed | M20: Fixed (was pending tester verify at close) | N20: https://github.com/cplreyes/ASPSI-DOH-UHC-CAPI-Development/issues/17
A21: R2 | B21: F2 PWA (HCW self-admin) | C21: F2 — HCW (PWA) | D21: 18 | E21: Render scale-style questions as a 2-way matrix instead of one-by-one | F21: Enhancement | G21: ux | H21: Low | I21: Direct | J21: 46137 | K21: 46143 | L21: Fixed | M21: Fixed (was pending tester verify at close) | N21: https://github.com/cplreyes/ASPSI-DOH-UHC-CAPI-Development/issues/18
A22: R3 | B22: F2 PWA (HCW self-admin) | C22: F2 — HCW (PWA) | D22: 19 | E22: Q4/Q9/Q10/Q11 — raw Zod error 'Expected number, received nan' leaks to UI | F22: Other | G22: validation | H22: High | I22: Direct | J22: 46137 | K22: 46143 | L22: Fixed | N22: https://github.com/cplreyes/ASPSI-DOH-UHC-CAPI-Development/issues/19
A23: R3 | B23: F2 PWA (HCW self-admin) | C23: F2 — HCW (PWA) | D23: 20 | E23: Inverted heading hierarchy — page H1 (18px) smaller than section H2 (24px) | F23: Other | G23: visual | H23: High | I23: Direct | J23: 46137 | K23: 46143 | L23: Fixed | N23: https://github.com/cplreyes/ASPSI-DOH-UHC-CAPI-Development/issues/20
A24: R3 | B24: F2 PWA (HCW self-admin) | C24: F2 — HCW (PWA) | D24: 21 | E24: Form layout pushed off-center on viewports ≥1600px | F24: Other | G24: visual | H24: High | I24: Direct | J24: 46137 | K24: 46143 | L24: Fixed | N24: https://github.com/cplreyes/ASPSI-DOH-UHC-CAPI-Development/issues/21
A25: R3 | B25: F2 PWA (HCW self-admin) | C25: F2 — HCW (PWA) | D25: 22 | E25: Disabled buttons fail WCAG AA contrast (opacity:0.5 on teal → ~2:1) | F25: Other | G25: visual | H25: High | I25: Direct | J25: 46137 | K25: 46143 | L25: Fixed | N25: https://github.com/cplreyes/ASPSI-DOH-UHC-CAPI-Development/issues/22
A26: R3 | B26: F2 PWA (HCW self-admin) | C26: F2 — HCW (PWA) | D26: 23 | E26: Default button height 32px below 44px tablet touch-target minimum | F26: Other | G26: ux | H26: Medium | I26: Direct | J26: 46137 | K26: 46143 | L26: Fixed | N26: https://github.com/cplreyes/ASPSI-DOH-UHC-CAPI-Development/issues/23
A27: R3 | B27: F2 PWA (HCW self-admin) | C27: F2 — HCW (PWA) | D27: 24 | E27: No visible focus ring on keyboard Tab navigation | F27: Other | G27: a11y | H27: Medium | I27: Direct | J27: 46137 | K27: 46143 | L27: Fixed | N27: https://github.com/cplreyes/ASPSI-DOH-UHC-CAPI-Development/issues/24
A28: R3 | B28: F2 PWA (HCW self-admin) | C28: F2 — HCW (PWA) | D28: 25 | E28: Q1_3 Middle Initial should be optional (apply same fix pattern as #14) | F28: Other | G28: validation | H28: Low | I28: Direct | J28: 46137 | K28: 46143 | L28: Fixed | N28: https://github.com/cplreyes/ASPSI-DOH-UHC-CAPI-Development/issues/25
A29: R3 | B29: F2 PWA (HCW self-admin) | C29: F2 — HCW (PWA) | D29: 26 | E29: Inconsistent Other label casing Q2 comma form vs Q5 parens form | F29: Other | G29: ux | H29: Low | I29: Direct | J29: 46137 | K29: 46143 | L29: Fixed | N29: https://github.com/cplreyes/ASPSI-DOH-UHC-CAPI-Development/issues/26
A30: R3 | B30: F2 PWA (HCW self-admin) | C30: F2 — HCW (PWA) | D30: 27 | E30: Locked sidebar sections appear as enabled buttons in a11y tree | F30: Other | G30: a11y | H30: Low | I30: Direct | J30: 46137 | K30: 46143 | L30: Fixed | N30: https://github.com/cplreyes/ASPSI-DOH-UHC-CAPI-Development/issues/27
A31: R3 | B31: F2 PWA (HCW self-admin) | C31: F2 — HCW (PWA) | D31: 28 | E31: Test Facility present in seed/cached facility list (also on staging) | F31: Other | G31: ux | H31: Low | I31: Direct | J31: 46137 | K31: 46143 | L31: Fixed | N31: https://github.com/cplreyes/ASPSI-DOH-UHC-CAPI-Development/issues/28
A32: R3 | B32: F2 PWA (HCW self-admin) | C32: F2 — HCW (PWA) | D32: 29 | E32: Right-edge floating arrow indicator clips off-screen at 375px viewport | F32: Other | G32: visual | H32: Low | I32: Direct | J32: 46137 | K32: 46143 | L32: Fixed | N32: https://github.com/cplreyes/ASPSI-DOH-UHC-CAPI-Development/issues/29
A33: R3 | B33: F2 PWA (HCW self-admin) | C33: F2 — HCW (PWA) | D33: 30 | E33: Header subtitle low contrast uses --muted instead of --muted-foreground | F33: Other | G33: visual | H33: Low | I33: Direct | J33: 46137 | K33: 46143 | L33: Fixed | N33: https://github.com/cplreyes/ASPSI-DOH-UHC-CAPI-Development/issues/30
A34: R3 | B34: F2 PWA (HCW self-admin) | C34: F2 — HCW (PWA) | D34: 33 | E34: Section F/G multi-select state pollution: selections unchecked when answering other questions | F34: Other | G34: ux | H34: High | I34: Direct | J34: 46138 | K34: 46142 | L34: Fixed | N34: https://github.com/cplreyes/ASPSI-DOH-UHC-CAPI-Development/issues/33
A35: R3 | B35: F2 PWA (HCW self-admin) | C35: F2 — HCW (PWA) | D35: 34 | E35: Cloudflare Pages auto-deploy on staging push is not firing | F35: Other | H35: High | I35: Direct | J35: 46138 | K35: 46142 | L35: Fixed | N35: https://github.com/cplreyes/ASPSI-DOH-UHC-CAPI-Development/issues/34
A36: R3 | B36: F2 PWA (HCW self-admin) | C36: F2 — HCW (PWA) | D36: 35 | E36: Worker PBKDF2 hash defaults (600k iters) exceed Cloudflare Workers runtime cap (100k) | F36: Other | H36: Medium | I36: Direct | J36: 46138 | K36: 46143 | L36: Fixed | N36: https://github.com/cplreyes/ASPSI-DOH-UHC-CAPI-Development/issues/35
A37: R3 | B37: F2 PWA (HCW self-admin) | C37: F2 — HCW (PWA) | D37: 45 | E37: F2 PWA `.env.local` stale — missing `VITE_F2_PROXY_URL` silently breaks staging build | F37: Other | H37: High | I37: Direct | J37: 46142 | K37: 46143 | L37: Fixed | N37: https://github.com/cplreyes/ASPSI-DOH-UHC-CAPI-Development/issues/45
A38: R3 | B38: F2 PWA (HCW self-admin) | C38: F2 — HCW (PWA) | D38: 46 | E38: F2 PWA enrollment: Enroll button no-ops on real-browser staging (verified token, no IDB write, no error) | F38: Other | H38: High | I38: Direct | J38: 46142 | K38: 46143 | L38: Fixed | N38: https://github.com/cplreyes/ASPSI-DOH-UHC-CAPI-Development/issues/46
A39: R3 | B39: F2 PWA (HCW self-admin) | C39: F2 — HCW (PWA) | D39: 52 | E39: EnrollmentScreen: Refresh button uses pre-enrollment deviceToken (empty) instead of verified token | F39: Other | G39: ux | H39: Medium | I39: Direct | J39: 46143 | K39: 46143 | L39: Fixed | N39: https://github.com/cplreyes/ASPSI-DOH-UHC-CAPI-Development/issues/52
A40: (none) | C40: F2 — HCW (PWA) | D40: 55 | E40: F2 PWA QA delta — 2026-05-04 | F40: Other | I40: Direct | J40: 46146 | K40: 46147 | L40: Fixed | N40: https://github.com/cplreyes/ASPSI-DOH-UHC-CAPI-Development/issues/55
A41: (none) | C41: F2 Admin Portal | D41: 56 | E41: [E4-APRT-044] RBAC role-version cache stale-entry — revoked permissions persist up to 60 min | F41: Bug | G41: security | H41: High | I41: Direct | J41: 46147 | K41: 46151 | L41: Fixed | N41: https://github.com/cplreyes/ASPSI-DOH-UHC-CAPI-Development/issues/56
A42: (none) | C42: F2 Admin Portal | D42: 57 | E42: [E4-APRT-045] JWT password_must_change enforced only client-side; bypassable via direct API | F42: Bug | G42: security | H42: Medium | I42: Direct | J42: 46147 | K42: 46151 | L42: Fixed | N42: https://github.com/cplreyes/ASPSI-DOH-UHC-CAPI-Development/issues/57
A43: (none) | C43: F2 Admin Portal | D43: 58 | E43: [E4-APRT-041] Create-HCW UI in Admin Portal — first-class Create form | F43: Enhancement | H43: Medium | I43: Direct | J43: 46147 | K43: 46151 | L43: Fixed | N43: https://github.com/cplreyes/ASPSI-DOH-UHC-CAPI-Development/issues/58
A44: (none) | C44: F2 Admin Portal | D44: 59 | E44: [E4-APRT-049a] Replace raw <button> with <Button> primitive — restore focus-visible ring | F44: Enhancement | G44: a11y | H44: High | I44: Direct | J44: 46147 | K44: 46151 | L44: Fixed | N44: https://github.com/cplreyes/ASPSI-DOH-UHC-CAPI-Development/issues/59
A45: (none) | C45: F2 Admin Portal | D45: 60 | E45: [E4-APRT-049b] Form inputs missing focus-visible ring — border-bottom-only affordance fix | F45: Enhancement | G45: a11y | H45: High | I45: Direct | J45: 46147 | K45: 46151 | L45: Fixed | N45: https://github.com/cplreyes/ASPSI-DOH-UHC-CAPI-Development/issues/60
A46: (none) | C46: F2 Admin Portal | D46: 61 | E46: [E4-APRT-049c] Drop rounded-full from filter pills + status badges + sidebar avatar | F46: Enhancement | G46: visual | H46: Medium | I46: Direct | J46: 46147 | K46: 46151 | L46: Fixed | N46: https://github.com/cplreyes/ASPSI-DOH-UHC-CAPI-Development/issues/61
A47: (none) | C47: F2 Admin Portal | D47: 62 | E47: [E4-APRT-049d] QuotaWidget uses --error for 80% Apps Script quota warning — switch to --warning | F47: Bug | G47: visual | H47: Medium | I47: Direct | J47: 46147 | K47: 46151 | L47: Fixed | N47: https://github.com/cplreyes/ASPSI-DOH-UHC-CAPI-Development/issues/62
A48: (none) | C48: General / Dev | D48: 63 | E48: [E4-APRT-037] Concurrency tests — two-admin reissue race / bulk import + role edit / cron + PWA submit | F48: Other | I48: Direct | J48: 46148 | K48: 46151 | L48: Fixed | N48: https://github.com/cplreyes/ASPSI-DOH-UHC-CAPI-Development/issues/63
A49: (none) | C49: General / Dev | D49: 64 | E49: [E4-APRT-042] Per-tester admin user accounts on prod — separate Shan/Kidd from carl_admin | F49: Other | I49: Direct | J49: 46148 | K49: 46151 | L49: Fixed | N49: https://github.com/cplreyes/ASPSI-DOH-UHC-CAPI-Development/issues/64
A50: (none) | C50: General / Dev | D50: 65 | E50: [E4-APRT-043] Production ADMIN_PASSWORD_HASH deletion (M10 sunset, prod side) | F50: Other | I50: Direct | J50: 46148 | K50: 46151 | L50: Fixed | N50: https://github.com/cplreyes/ASPSI-DOH-UHC-CAPI-Development/issues/65
A51: (none) | C51: General / Dev | D51: 66 | E51: [E4-APRT-048] Users — last_login_at write path on successful login (half-built bug) | F51: Other | I51: Direct | J51: 46148 | K51: 46151 | L51: Fixed | N51: https://github.com/cplreyes/ASPSI-DOH-UHC-CAPI-Development/issues/66
A52: (none) | C52: General / Dev | D52: 67 | E52: [E4-APRT-049e] ReissueTokenModal doesn't dismiss on Escape key — fix per DESIGN.md | F52: Other | I52: Direct | J52: 46148 | K52: 46151 | L52: Fixed | N52: https://github.com/cplreyes/ASPSI-DOH-UHC-CAPI-Development/issues/67
A53: R2 | B53: F2 PWA (HCW self-admin) | C53: F2 Admin Portal | D53: 68 | E53: #4 – Reference: Admin Portal Layout | F53: Bug | H53: High | I53: Direct | J53: 46149 | K53: 46151 | L53: Fixed | M53: Fixed (was pending tester verify at close) | N53: https://github.com/cplreyes/ASPSI-DOH-UHC-CAPI-Development/issues/68
A54: R2 | B54: F2 PWA (HCW self-admin) | C54: F2 Admin Portal | D54: 69 | E54: 5.1 Login + session | F54: Bug | G54: ux | H54: Low | I54: Direct | J54: 46149 | K54: 46151 | L54: Fixed | M54: Fixed (was pending tester verify at close) | N54: https://github.com/cplreyes/ASPSI-DOH-UHC-CAPI-Development/issues/69
A55: R2 | B55: F2 PWA (HCW self-admin) | C55: F2 Admin Portal | D55: 70 | E55: Login + session | F55: Bug | I55: Direct | J55: 46149 | K55: 46151 | L55: Fixed | M55: Fixed (was pending tester verify at close) | N55: https://github.com/cplreyes/ASPSI-DOH-UHC-CAPI-Development/issues/70
A56: R2 | B56: F2 PWA (HCW self-admin) | C56: F2 Admin Portal | D56: 71 | E56: Login + session | F56: Bug | I56: Direct | J56: 46149 | K56: 46151 | L56: Fixed | M56: Fixed (was pending tester verify at close) | N56: https://github.com/cplreyes/ASPSI-DOH-UHC-CAPI-Development/issues/71
A57: R2 | B57: F2 PWA (HCW self-admin) | C57: F2 Admin Portal | D57: 72 | E57: Login + session | F57: Bug | I57: Direct | J57: 46149 | K57: 46151 | L57: Fixed | M57: Fixed (was pending tester verify at close) | N57: https://github.com/cplreyes/ASPSI-DOH-UHC-CAPI-Development/issues/72
A58: (none) | C58: General / Dev | D58: 73 | E58: Login + session | F58: Other | I58: Direct | J58: 46149 | K58: 46149 | L58: Fixed | N58: https://github.com/cplreyes/ASPSI-DOH-UHC-CAPI-Development/issues/73
A59: (none) | C59: General / Dev | D59: 74 | E59: Login + session | F59: Bug | I59: Direct | J59: 46149 | K59: 46149 | L59: Deferred | M59: Not actioned / deferred | N59: https://github.com/cplreyes/ASPSI-DOH-UHC-CAPI-Development/issues/74
A60: (none) | C60: General / Dev | D60: 75 | E60: Login + session | F60: Bug | I60: Direct | J60: 46149 | K60: 46149 | L60: Fixed | N60: https://github.com/cplreyes/ASPSI-DOH-UHC-CAPI-Development/issues/75
A61: (none) | C61: General / Dev | D61: 76 | E61: 5.2 Data dashboard — Responses sub-tab | F61: Bug | I61: Direct | J61: 46149 | K61: 46149 | L61: Fixed | N61: https://github.com/cplreyes/ASPSI-DOH-UHC-CAPI-Development/issues/76
A62: (none) | C62: General / Dev | D62: 77 | E62: Data dashboard — Responses sub-tab | F62: Bug | I62: Direct | J62: 46149 | K62: 46149 | L62: Fixed | N62: https://github.com/cplreyes/ASPSI-DOH-UHC-CAPI-Development/issues/77
A63: R2 | B63: F2 PWA (HCW self-admin) | C63: F2 Admin Portal | D63: 78 | E63: Data dashboard — Responses sub-tab - Other Observation | F63: Bug | I63: Direct | J63: 46149 | K63: 46151 | L63: Fixed | M63: Fixed (was pending tester verify at close) | N63: https://github.com/cplreyes/ASPSI-DOH-UHC-CAPI-Development/issues/78
A64: R2 | B64: F2 PWA (HCW self-admin) | C64: F2 Admin Portal | D64: 79 | E64: 5.3 Data dashboard — Audit sub-tab | F64: Bug | I64: Direct | J64: 46149 | K64: 46151 | L64: Fixed | M64: Fixed (was pending tester verify at close) | N64: https://github.com/cplreyes/ASPSI-DOH-UHC-CAPI-Development/issues/79
A65: R2 | B65: F2 PWA (HCW self-admin) | C65: F2 Admin Portal | D65: 80 | E65: Data dashboard — Audit sub-tab | F65: Bug | I65: Direct | J65: 46149 | K65: 46151 | L65: Fixed | M65: Fixed (was pending tester verify at close) | N65: https://github.com/cplreyes/ASPSI-DOH-UHC-CAPI-Development/issues/80
A66: (none) | C66: General / Dev | D66: 81 | E66: Data dashboard — Audit sub-tab | F66: Bug | I66: Direct | J66: 46149 | K66: 46149 | L66: Fixed | N66: https://github.com/cplreyes/ASPSI-DOH-UHC-CAPI-Development/issues/81
A67: R2 | B67: F2 PWA (HCW self-admin) | C67: F2 Admin Portal | D67: 82 | E67: Data dashboard — Audit sub-tab - Other Observations | F67: Bug | I67: Direct | J67: 46149 | K67: 46151 | L67: Fixed | M67: Fixed (was pending tester verify at close) | N67: https://github.com/cplreyes/ASPSI-DOH-UHC-CAPI-Development/issues/82
A68: R2 | B68: F2 PWA (HCW self-admin) | C68: F2 Admin Portal | D68: 83 | E68: Data dashboard — DLQ sub-tab | F68: Bug | I68: Direct | J68: 46149 | K68: 46151 | L68: Fixed | M68: Fixed (was pending tester verify at close) | N68: https://github.com/cplreyes/ASPSI-DOH-UHC-CAPI-Development/issues/83
A69: R2 | B69: F2 PWA (HCW self-admin) | C69: F2 Admin Portal | D69: 84 | E69: Data dashboard — DLQ sub-tab | F69: Bug | H69: Medium | I69: Direct | J69: 46149 | K69: 46151 | L69: Fixed | M69: Fixed (was pending tester verify at close) | N69: https://github.com/cplreyes/ASPSI-DOH-UHC-CAPI-Development/issues/84
A70: R2 | B70: F2 PWA (HCW self-admin) | C70: F2 Admin Portal | D70: 85 | E70: 5.5 Data dashboard — HCWs sub-tab + Reissue Token flow | F70: Bug | I70: Direct | J70: 46149 | K70: 46151 | L70: Fixed | M70: Fixed (was pending tester verify at close) | N70: https://github.com/cplreyes/ASPSI-DOH-UHC-CAPI-Development/issues/85
A71: R2 | B71: F2 PWA (HCW self-admin) | C71: F2 Admin Portal | D71: 86 | E71: Data dashboard — HCWs sub-tab + Reissue Token flow | F71: Bug | I71: Direct | J71: 46149 | K71: 46151 | L71: Fixed | M71: Fixed (was pending tester verify at close) | N71: https://github.com/cplreyes/ASPSI-DOH-UHC-CAPI-Development/issues/86
A72: R2 | B72: F2 PWA (HCW self-admin) | C72: F2 Admin Portal | D72: 87 | E72: Data dashboard — HCWs sub-tab + Reissue Token flow | F72: Bug | I72: Direct | J72: 46149 | K72: 46151 | L72: Fixed | M72: Fixed (was pending tester verify at close) | N72: https://github.com/cplreyes/ASPSI-DOH-UHC-CAPI-Development/issues/87
A73: R2 | B73: F2 PWA (HCW self-admin) | C73: F2 Admin Portal | D73: 88 | E73: Data dashboard — HCWs sub-tab + Reissue Token flow | F73: Bug | I73: Direct | J73: 46149 | K73: 46151 | L73: Fixed | M73: Fixed (was pending tester verify at close) | N73: https://github.com/cplreyes/ASPSI-DOH-UHC-CAPI-Development/issues/88
A74: R2 | B74: F2 PWA (HCW self-admin) | C74: F2 Admin Portal | D74: 89 | E74: 5.7 Reports — Map Report sub-tab | F74: Bug | H74: High | I74: Direct | J74: 46149 | K74: 46151 | L74: Fixed | M74: Fixed (was pending tester verify at close) | N74: https://github.com/cplreyes/ASPSI-DOH-UHC-CAPI-Development/issues/89
A75: R2 | B75: F2 PWA (HCW self-admin) | C75: F2 Admin Portal | D75: 90 | E75: Reports — Map Report sub-tab | F75: Bug | H75: High | I75: Direct | J75: 46149 | K75: 46151 | L75: Fixed | N75: https://github.com/cplreyes/ASPSI-DOH-UHC-CAPI-Development/issues/90
A76: R2 | B76: F2 PWA (HCW self-admin) | C76: F2 Admin Portal | D76: 91 | E76: 5.9 Apps & Settings — Files sub-tab | F76: Bug | I76: Direct | J76: 46149 | K76: 46151 | L76: Fixed | N76: https://github.com/cplreyes/ASPSI-DOH-UHC-CAPI-Development/issues/91
A77: R2 | B77: F2 PWA (HCW self-admin) | C77: F2 Admin Portal | D77: 92 | E77: Apps & Settings — Files sub-tab | F77: Bug | I77: Direct | J77: 46149 | K77: 46151 | L77: Fixed | N77: https://github.com/cplreyes/ASPSI-DOH-UHC-CAPI-Development/issues/92
A78: R2 | B78: F2 PWA (HCW self-admin) | C78: F2 Admin Portal | D78: 93 | E78: Apps & Settings — Files sub-tab | F78: Bug | G78: i18n | H78: Medium | I78: Direct | J78: 46149 | K78: 46151 | L78: Fixed | N78: https://github.com/cplreyes/ASPSI-DOH-UHC-CAPI-Development/issues/93
A79: R2 | B79: F2 PWA (HCW self-admin) | C79: F2 Admin Portal | D79: 94 | E79: 5.10 Apps & Settings — Data Settings sub-tab | F79: Bug | I79: Direct | J79: 46149 | K79: 46151 | L79: Fixed | N79: https://github.com/cplreyes/ASPSI-DOH-UHC-CAPI-Development/issues/94
A80: R2 | B80: F2 PWA (HCW self-admin) | C80: F2 Admin Portal | D80: 95 | E80: Apps & Settings — Data Settings sub-tab | F80: Bug | I80: Direct | J80: 46149 | K80: 46151 | L80: Fixed | N80: https://github.com/cplreyes/ASPSI-DOH-UHC-CAPI-Development/issues/95
A81: R2 | B81: F2 PWA (HCW self-admin) | C81: F2 Admin Portal | D81: 96 | E81: Apps & Settings — Data Settings sub-tab | F81: Bug | I81: Direct | J81: 46149 | K81: 46151 | L81: Fixed | N81: https://github.com/cplreyes/ASPSI-DOH-UHC-CAPI-Development/issues/96
A82: R2 | B82: F2 PWA (HCW self-admin) | C82: F2 Admin Portal | D82: 97 | E82: 5.11 Apps & Settings — Apps Script Quota sub-tab | F82: Bug | I82: Direct | J82: 46149 | K82: 46151 | L82: Fixed | N82: https://github.com/cplreyes/ASPSI-DOH-UHC-CAPI-Development/issues/97
A83: R2 | B83: F2 PWA (HCW self-admin) | C83: F2 Admin Portal | D83: 98 | E83: 5.12 Users dashboard | F83: Bug | H83: Medium | I83: Direct | J83: 46149 | K83: 46151 | L83: Fixed | N83: https://github.com/cplreyes/ASPSI-DOH-UHC-CAPI-Development/issues/98
A84: R2 | B84: F2 PWA (HCW self-admin) | C84: F2 Admin Portal | D84: 99 | E84: Users dashboard | F84: Bug | I84: Direct | J84: 46149 | K84: 46151 | L84: Fixed | N84: https://github.com/cplreyes/ASPSI-DOH-UHC-CAPI-Development/issues/99
A85: R2 | B85: F2 PWA (HCW self-admin) | C85: F2 Admin Portal | D85: 100 | E85: 5.12 Users dashboard | F85: Other | H85: Low | I85: Direct | J85: 46149 | K85: 46151 | L85: Fixed | N85: https://github.com/cplreyes/ASPSI-DOH-UHC-CAPI-Development/issues/100
A86: (none) | C86: General / Dev | D86: 101 | E86: 5.1 Login + Session | F86: Other | I86: Direct | J86: 46149 | K86: 46149 | L86: Fixed | N86: https://github.com/cplreyes/ASPSI-DOH-UHC-CAPI-Development/issues/101
A87: R2 | B87: F2 PWA (HCW self-admin) | C87: F2 Admin Portal | D87: 102 | E87: 5.14 RBAC + persona switching (the spec story) | F87: Bug | G87: security | H87: High | I87: Direct | J87: 46149 | K87: 46151 | L87: Fixed | N87: https://github.com/cplreyes/ASPSI-DOH-UHC-CAPI-Development/issues/102
A88: R2 | B88: F2 PWA (HCW self-admin) | C88: F2 Admin Portal | D88: 103 | E88: RBAC + persona switching (the spec story) | F88: Bug | I88: Direct | J88: 46149 | K88: 46151 | L88: Fixed | N88: https://github.com/cplreyes/ASPSI-DOH-UHC-CAPI-Development/issues/103
A89: R2 | B89: F2 PWA (HCW self-admin) | C89: F2 Admin Portal | D89: 104 | E89: RB.E2 RBAC + persona switching (the spec story) | F89: Other | I89: Direct | J89: 46149 | K89: 46151 | L89: Fixed | N89: https://github.com/cplreyes/ASPSI-DOH-UHC-CAPI-Development/issues/104
A90: R2 | B90: F2 PWA (HCW self-admin) | C90: F2 Admin Portal | D90: 105 | E90: 5.16 Sub-tab pattern + sidebar (N.H2) | F90: Other | I90: Direct | J90: 46149 | K90: 46151 | L90: Fixed | N90: https://github.com/cplreyes/ASPSI-DOH-UHC-CAPI-Development/issues/105
A91: R2 | B91: F2 PWA (HCW self-admin) | C91: F2 Admin Portal | D91: 106 | E91: 5.17 Encode dashboard (paper-encoded path) (EH.1) | F91: Other | I91: Direct | J91: 46149 | K91: 46151 | L91: Deferred | M91: Not actioned / deferred | N91: https://github.com/cplreyes/ASPSI-DOH-UHC-CAPI-Development/issues/106
A92: R2 | B92: F2 PWA (HCW self-admin) | C92: F2 Admin Portal | D92: 107 | E92: 5.17 Encode dashboard (paper-encoded path) | F92: Other | I92: Direct | J92: 46149 | K92: 46151 | L92: Deferred | M92: Not actioned / deferred | N92: https://github.com/cplreyes/ASPSI-DOH-UHC-CAPI-Development/issues/107
A93: R2 | B93: F2 PWA (HCW self-admin) | C93: F2 — HCW (PWA) | D93: 108 | E93: (A.1.E2) 5.1 Token-paste enrollment | F93: Bug | G93: ux | H93: Low | I93: Direct | J93: 46149 | K93: 46151 | L93: Fixed | N93: https://github.com/cplreyes/ASPSI-DOH-UHC-CAPI-Development/issues/108
A94: R2 | B94: F2 PWA (HCW self-admin) | C94: F2 — HCW (PWA) | D94: 109 | E94: (A.1.E3) 5.1 Token-paste enrollment | F94: Bug | G94: sync | H94: Low | I94: Direct | J94: 46149 | K94: 46151 | L94: Fixed | N94: https://github.com/cplreyes/ASPSI-DOH-UHC-CAPI-Development/issues/109
A95: R2 | B95: F2 PWA (HCW self-admin) | C95: F2 — HCW (PWA) | D95: 110 | E95: (A.2.E8) Q9 - 5.2 Section A — Healthcare Worker Profile (Q1–Q11) | F95: Bug | G95: validation | H95: Medium | I95: Direct | J95: 46149 | K95: 46151 | L95: Fixed | N95: https://github.com/cplreyes/ASPSI-DOH-UHC-CAPI-Development/issues/110
A96: R2 | B96: F2 PWA (HCW self-admin) | C96: F2 — HCW (PWA) | D96: 111 | E96: (B.E1) 5.3 Section B — UHC Awareness (Q25) | F96: Other | I96: Direct | J96: 46149 | K96: 46150 | L96: Fixed | N96: https://github.com/cplreyes/ASPSI-DOH-UHC-CAPI-Development/issues/111
A97: R2 | B97: F2 PWA (HCW self-admin) | C97: F2 — HCW (PWA) | D97: 112 | E97: 5. (B.E2) 5.3 Section B — UHC Awareness (Q25) | F97: Other | G97: validation | H97: High | I97: Direct | J97: 46149 | K97: 46151 | L97: Fixed | N97: https://github.com/cplreyes/ASPSI-DOH-UHC-CAPI-Development/issues/112
A98: R2 | B98: F2 PWA (HCW self-admin) | C98: F2 — HCW (PWA) | D98: 114 | E98: (C.E1) 5.4 Section C — YAKAP/Konsulta (Q31–Q40, role-gated) | F98: Bug | G98: skip-logic | H98: Critical | I98: Direct | J98: 46150 | K98: 46151 | L98: Fixed | N98: https://github.com/cplreyes/ASPSI-DOH-UHC-CAPI-Development/issues/114
A99: R2 | B99: F2 PWA (HCW self-admin) | C99: F2 — HCW (PWA) | D99: 115 | E99: (C.E2) 5.4 Section C — YAKAP/Konsulta (Q31–Q40, role-gated) | F99: Bug | G99: skip-logic | H99: Medium | I99: Direct | J99: 46150 | K99: 46151 | L99: Fixed | N99: https://github.com/cplreyes/ASPSI-DOH-UHC-CAPI-Development/issues/115
A100: R2 | B100: F2 PWA (HCW self-admin) | C100: F2 — HCW (PWA) | D100: 116 | E100: (Q44) 5.5 Section D — NBB/ZBB Awareness (Q41–Q47, role-gated) | F100: Bug | G100: skip-logic | H100: High | I100: Direct | J100: 46150 | K100: 46151 | L100: Fixed | N100: https://github.com/cplreyes/ASPSI-DOH-UHC-CAPI-Development/issues/116
A101: R2 | B101: F2 PWA (HCW self-admin) | C101: F2 — HCW (PWA) | D101: 117 | E101: Section E1 and E2 | F101: Enhancement | G101: skip-logic | I101: Direct | J101: 46150 | K101: 46151 | L101: Fixed | N101: https://github.com/cplreyes/ASPSI-DOH-UHC-CAPI-Development/issues/117
...
