Workbook

Sheet Summary
A1: DOH Review Comments (via Xylee “XJ” Javier) — Findings & Fixes Summary
A2: ASPSI–DOH UHC Survey Year 2 CAPI · compiled 2026-08-14 · statuses verified against the current build
A4: What this file covers
A5: • XJ's PAPI-vs-CAPI screenshot reviews (July 2026) — 149 per-question findings: 63 on HCW (F2) and 86 on Household (F4). Each finding is one row on the instrument tabs, with XJ's comment verbatim and the current-build status.
A6: • The DOH June-2026 questionnaire comment batch (also relayed via XJ) for F1/F3/F4 — summarized at theme level on the F1/F3/F4 tabs. Per Dr. Myra Silva-Javier's ruling (2026-06-12) these are PARKED: the April-20 questionnaire is the accepted build baseline.
A7: • DOH-agreed content changes that WERE built (PhilHealth follow-up reinstatements; June-5 Deliverable-2 tool alignment) — rows marked 'Fixed in build'.
A9: Key result of the August 2026 verification
A10: • All 88 'Other (specify) field missing' findings were re-audited against the live instruments: 85 verified present (50 F4 dictionary fields, 35 F2 PWA companion fields with required 'Please specify' validation) and 3 not applicable (F2 Q109 is free-text; F2 Q112/Q123 have no Other option). 0 real gaps.
A11: • Multi-select exclusivity (an XJ ask on both instruments) now HARD-blocks invalid combinations — shipped class-wide in the pretest fix waves (Aug 2026).
A12: • The remaining design/UX/process items need no build change: they are answered by documentation (skip/validation matrix + test login + current screenshots), are deliberate design, or await an ASPSI/DOH decision (parked).
A14: How to read the Status column
A15: • Fixed in build — a change was made and deployed. • Verified in build — the asked-for feature already exists (confirmed by audit).
... A19: Counts by status
A20: Status | B20: F1 | C20: F2 | D20: F3 | E20: F4 | F20: Total
A21: Fixed in build | B21: =COUNTIF('Facility Head (F1)'!$E$4:$E$200,$A21) -> 0 | C21: =COUNTIF('HCW (F2)'!$E$4:$E$200,$A21) -> 0 | D21: =COUNTIF('Patient (F3)'!$E$4:$E$200,$A21) -> 2 | E21: =COUNTIF('Household (F4)'!$E$4:$E$200,$A21) -> 3 | F21: =SUM(B21:E21) -> 5
A22: Verified in build | B22: =COUNTIF('Facility Head (F1)'!$E$4:$E$200,$A22) -> 0 | C22: =COUNTIF('HCW (F2)'!$E$4:$E$200,$A22) -> 35 | D22: =COUNTIF('Patient (F3)'!$E$4:$E$200,$A22) -> 0 | E22: =COUNTIF('Household (F4)'!$E$4:$E$200,$A22) -> 50 | F22: =SUM(B22:E22) -> 85
A23: Already in build | B23: =COUNTIF('Facility Head (F1)'!$E$4:$E$200,$A23) -> 0 | C23: =COUNTIF('HCW (F2)'!$E$4:$E$200,$A23) -> 8 | D23: =COUNTIF('Patient (F3)'!$E$4:$E$200,$A23) -> 0 | E23: =COUNTIF('Household (F4)'!$E$4:$E$200,$A23) -> 8 | F23: =SUM(B23:E23) -> 16
A24: By design | B24: =COUNTIF('Facility Head (F1)'!$E$4:$E$200,$A24) -> 0 | C24: =COUNTIF('HCW (F2)'!$E$4:$E$200,$A24) -> 2 | D24: =COUNTIF('Patient (F3)'!$E$4:$E$200,$A24) -> 0 | E24: =COUNTIF('Household (F4)'!$E$4:$E$200,$A24) -> 4 | F24: =SUM(B24:E24) -> 6
A25: Docs to provide | B25: =COUNTIF('Facility Head (F1)'!$E$4:$E$200,$A25) -> 0 | C25: =COUNTIF('HCW (F2)'!$E$4:$E$200,$A25) -> 7 | D25: =COUNTIF('Patient (F3)'!$E$4:$E$200,$A25) -> 0 | E25: =COUNTIF('Household (F4)'!$E$4:$E$200,$A25) -> 3 | F25: =SUM(B25:E25) -> 10
A26: Parked — DOH decision | B26: =COUNTIF('Facility Head (F1)'!$E$4:$E$200,$A26) -> 1 | C26: =COUNTIF('HCW (F2)'!$E$4:$E$200,$A26) -> 8 | D26: =COUNTIF('Patient (F3)'!$E$4:$E$200,$A26) -> 1 | E26: =COUNTIF('Household (F4)'!$E$4:$E$200,$A26) -> 20 | F26: =SUM(B26:E26) -> 30
A27: Not applicable | B27: =COUNTIF('Facility Head (F1)'!$E$4:$E$200,$A27) -> 0 | C27: =COUNTIF('HCW (F2)'!$E$4:$E$200,$A27) -> 3 | D27: =COUNTIF('Patient (F3)'!$E$4:$E$200,$A27) -> 0 | E27: =COUNTIF('Household (F4)'!$E$4:$E$200,$A27) -> 0 | F27: =SUM(B27:E27) -> 3
A28: Total rows | B28: =SUM(B21:B27) -> 1 | C28: =SUM(C21:C27) -> 63 | D28: =SUM(D21:D27) -> 3 | E28: =SUM(E21:E27) -> 88 | F28: =SUM(B28:E28) -> 155

Sheet Facility Head (F1)
A1: Facility Head (F1) — DOH comments via XJ
A2: XJ's July-2026 PAPI-vs-CAPI screenshot review covered F2 and F4 only — no per-question XJ findings exist for F1. Rows below are the F1 items from the DOH June-2026 questionnaire comment batch (relayed via XJ), per-item matrix held in ASPSI's comment thread/Google Doc.
A3: Question | B3: Comments | C3: Category of bug | D3: Fixes | E3: Status | F3: GitHub ref
A4: Q19, Q21, Q23, Q25, Q27, Q29, Q31, Q39–Q48 (+ EMR / MoU / NBB / ZBB items) | B4: DOH proposed restructuring ~18 questions into a two-step pattern: “Has this changed since 2019?” then “Is the change a result of the UHC Act?”. | C4: Questionnaire redesign (content) | D4: No build change — parked per Dr. Myra Silva-Javier's ruling (2026-06-12): the April-20 questionnaire is the accepted baseline; June comments are answered with finality only if they resurface via SJREB review, PSA review, or pre-testing. Adopting them mid-stream was quantified (2026-06-19) as an 8–10-week slip. | E4: Parked — DOH decision | F4: —

Sheet HCW (F2)
A1: Healthcare Worker (F2 / PWA) — 63 XJ findings
A2: Source: XJ PAPI-vs-CAPI HCW review (July 2026), triaged one GitHub issue per finding under epic #849 (label from-doh-review-xj-2026-07). Comments are XJ's, verbatim from the triage. Statuses re-verified against the current PWA build, August 2026.
A3: Question | B3: Comments | C3: Category of bug | D3: Fixes | E3: Status | F3: GitHub ref
A4: form-wide | B4: The HCW Survey CAPI appears to use a different interface. Clarify whether a different platform/version is used and the rationale; consider consistent UX across instruments. (XJ rates the HCW/PWA interface the more polished one — section headers, progress indicators, no repeated question text.) | C4: Form structure / sections | D4: Working as designed — F2 is the PWA by design (self-administered, online/offline); F1/F3/F4 are CSPro. Document the rationale; XJ recommends the others match F2, not the reverse. | E4: By design | F4: #851
A5: documentation | B5: Since the tools were submitted to PSA, documentation should reflect the complete/near-final CAPI; representative screenshots of full interface + functionality across instruments would enable a more accurate review. | C5: Process / documentation | D5: No build change — to be answered with the evidence pack (skip/validation matrix + test login). Evidence: supply current screenshots + a test login. | E5: Docs to provide | F5: #852
A6: sections | B6: The submitted screenshots do not show the Questionnaire number, Informed Consent Form, Field Control, and Health Facility & Geographic Identification sections present in PAPI. Clarify how implemented in CAPI, and whether the offline version matches the online interface. | C6: Form structure — consent | D6: Already implemented in the current build — Consent gate shipped (F2 R6 #808); enrolment carries facility/QN. Screenshot gap — attach current screens; state offline parity. No code change needed; evidence = current screens. | E6: Already in build | F6: #853
A7: navigation | B7: Screenshots do not show navigation controls. Clarify how respondents navigate, especially when reviewing/correcting previous responses. | C7: Platform behavior / UX | D7: Already implemented in the current build — PWA has section navigation. Screenshot/documentation gap. No code change needed; evidence = current screens. | E7: Already in build | F7: #854
A8: autosave | B8: Clarify whether the app autosaves on connectivity loss, device interruption, or unexpected closure, and describe data-recovery mechanisms. | C8: Platform behavior / UX | D8: Already implemented in the current build — F2 has IndexedDB autosave in production. Document it. No code change needed; evidence = current screens. | E8: Already in build | F8: #855
A9: resume | B9: Clarify whether the system can detect an incomplete questionnaire and allow resuming from the last saved point. | C9: Platform behavior / UX | D9: Already implemented in the current build — F2 supports resume in production. Document it. No code change needed; evidence = current screens. | E9: Already in build | F9: #856
A10: timeout | B10: Indicate whether sessions time out/expire; if so, how unsaved responses are handled and whether users are notified before expiry. | C10: Platform behavior / UX | D10: Working as designed — Design point — state the behaviour (self-administered PWA). | E10: By design | F10: #857
A11: required-fields | B11: The HCW CAPI uses a red asterisk (*) to mark fields but provides no legend. If it marks required fields, add a brief note clarifying its meaning. | C11: Display / wording | D11: No build change — change candidate parked per Dr. Myra Silva-Javier's ruling (2026-06-12; April-20 questionnaire is the accepted baseline); needs an ASPSI/DOH decision before building. Small UX add; candidate. | E11: Parked — DOH decision | F11: #858
A12: skip-matrix | B12: Skip rules are omitted from the interface (correct for CAPI) but the reviewer cannot verify programmed skips/validations without test access, and screenshots don't demonstrate validation checks. Provide a skip-pattern matrix, programming specs, or a test environment. | C12: Process / documentation | D12: No build change — to be answered with the evidence pack (skip/validation matrix + test login). Highest-leverage answer: one skip/validation matrix + a test login (verify_questions.py output is a starting point). | E12: Docs to provide | F12: #859
A13: validation-exclusive | B13: For multiple-answer questions, automatically block selecting 'None of the above'/'Refuse'/'Not applicable'/'Don't know' if 'Other (Specify)' or any listed option is chosen. | C13: Validation — answer rules | D13: Already implemented in the current build — the PWA enforces exclusivity (selecting a listed/Other option blocks or clears exclusive options), shipped before the review and covered by automated exclusivity tests. Evidence = current-build demo. | E13: Already in build | F13: #860
A14: validation-simultaneous | B14: For multiple-answer questions, prevent simultaneous selection of the exclusive options (None/Refuse/NA/DK). | C14: Validation — answer rules | D14: Already implemented in the current build — mutually-exclusive options cannot be selected together in the PWA; enforcement predates the review. Evidence = current-build demo. | E14: Already in build | F14: #861
... A66: Q124 | B66: XJ flags that all questions with an 'Other (specify)' option lack the 'specify' data field; Q124 is on that list. Ensure the 'Other' option exposes a free-text capture. | C66: Data capture — Other (specify) field | D66: VERIFIED in current build (2026-08 audit of the PWA schema) — companion field Q124_other exists with a required 'Please specify' validation when Other is chosen. | E66: Verified in build | F66: #949

Sheet Patient (F3)
A1: Patient (F3) — DOH comments via XJ
A2: XJ's July-2026 PAPI-vs-CAPI screenshot review covered F2 and F4 only — no per-question XJ findings exist for F3. Rows below: F3 items from the DOH June-2026 comment batch (parked) plus DOH-driven changes that WERE built.
A3: Question | B3: Comments | C3: Category of bug | D3: Fixes | E3: Status | F3: GitHub ref
A4: Q38.1 / Q38.2 | B4: DOH-agreed reinstatement of the PhilHealth registration follow-ups: when the respondent registered/received the PIN (Q38.1) and why not registered (Q38.2). (Separate DOH-agreed batch, not part of the parked June comments.) | C4: DOH-agreed content change | D4: Fixed — built and deployed to CSWeb during UAT Round 5 (GitHub #764, closed 2026-06-26, deployed 06-27). Live in the F3 dictionary as Q38_1_PIN_WHEN and Q38_2_WHY_NOT_REG (tick-all). “I don't know” follows the locked missing-value standard (−98). | E4: Fixed in build | F4: #764
A5: Q92, Q96, Q107, Q109 | B5: Payment-source matrices: amount-bearing sources reordered to the top, and Q109 gains a “Donation” option — changes DOH adopted into the June-5 English tool that ships inside Deliverable 2 (the version the pretest testers held and all 7 translations were made from). | C5: Value sets / question order | D5: Fixed — CAPI aligned to the June-5 Deliverable-2 tool in F3 v2.0.0, deployed 2026-08-13 (tickets #1151/#1152/#1156/#1158). Breaking data-shape change handled: codebook regenerated; tabulation owner flagged (code-keyed breakdowns); pretest-case remap expected. | E5: Fixed in build | F5: #1151–#1158
A6: After Q18 (new block); Q24–Q28; items #168–171 | B6: June-2026 batch: add a new household-expenditure block after Q18; replace Q24–Q28 with the FIES asset battery; add billed-vs-paid amount items (#168–171). | C6: Questionnaire redesign (content) | D6: No build change — parked per Dr. Myra Silva-Javier's ruling (2026-06-12; April-20 baseline). Revisited only if the ask resurfaces via SJREB / PSA / pretest, or if it already appears in the June-5 Deliverable-2 tool (which is checked before deferring any “the paper says X” ticket). | E6: Parked — DOH decision | F6: —

Sheet Household (F4)
A1: Household (F4 / CSPro) — 86 XJ findings + DOH-driven changes
A2: Source: XJ PAPI-vs-CAPI Household review (July 2026), triaged one GitHub issue per finding under epic #850 (label from-doh-review-xj-2026-07). Comments are XJ's, verbatim from the triage. Statuses re-verified against the current F4 dictionary/generators, August 2026.
A3: Question | B3: Comments | C3: Category of bug | D3: Fixes | E3: Status | F3: GitHub ref
A4: Q45.1 / Q45.2 | B4: DOH-agreed reinstatement of the PhilHealth registration follow-ups: when the respondent registered/received the PIN (Q45.1) and why not registered (Q45.2). (Separate DOH-agreed batch, not part of XJ's July review.) | C4: DOH-agreed content change | D4: Fixed — built and deployed to CSWeb during UAT Round 5 (GitHub #794 + #795, closed and deployed 2026-06-25). Live in the F4 dictionary as Q45_1_PIN_REG_WHEN and Q45_2_WHY_NOT_REG (+ _OTHER_TXT). | E4: Fixed in build | F4: #794 #795
A5: Whole instrument | B5: June-2026 batch (CONTESTED): DOH wants its April-15 PIDS/DHS-style household questionnaire restructure adopted; the UP/ASPSI team was instructed NOT to follow it. | C5: Questionnaire redesign (content) | D5: No build change — parked per Dr. Myra Silva-Javier's ruling (2026-06-12; April-20 baseline). XJ's own July screenshot review turned out clarification/observation-heavy, not the feared restructure. | E5: Parked — DOH decision | F5: —
A6: consent | B6: The Consent Form section from PAPI is not found in CAPI. | C6: Form structure — consent | D6: Already implemented in the current build — Consent/break-off handling exists; screenshot/clarify implementation. No code change needed; evidence = current screens. | E6: Already in build | F6: #876
A7: field-control | B7: Field Control appears at the end. Clarify whether these fields are completed only on completion or can be accessed/updated during the interview, particularly for incomplete interviews requiring callbacks and resumption. | C7: Field control / visits | D7: Already implemented in the current build — Break-off + disposition model handles this; document callback flow. No code change needed; evidence = current screens. | E7: Already in build | F7: #877
A8: disposition | B8: Justify the April change of 'Refused' to 'Withdraw Participation/Consent'; clarify category + code-order differences vs Facility/HCW forms (Completed, Postponed, Refused, Incomplete); harmonize unless intentional/documented. | C8: Form structure — consent | D8: Working as designed — Deliberate; document rationale + cross-instrument harmonization intent. | E8: By design | F8: #878
A9: visit-date | B9: The facility visit-date format differs (PAPI Month-Day-Year vs CAPI YYYYMMDD). Provide rationale. | C9: Value sets / codes / formats | D9: Working as designed — Design choice; document. | E9: By design | F9: #879
A10: visits | B10: Confirm how many visits are allowed; only first and final are recorded, but the manual allows up to three callbacks in the Visit Sheet. Clarify how intermediate visits/callbacks are documented in CAPI. | C10: Field control / visits | D10: No build change — to be answered with the evidence pack (skip/validation matrix + test login). Map callbacks to the CAPI break-off/disposition model; document. | E10: Docs to provide | F10: #880
A11: navigation | B11: Screenshots don't show navigation controls (Next/Back/Go-To/navigator). Clarify how enumerators navigate/correct previous responses. | C11: Platform behavior / UX | D11: Already implemented in the current build — CSEntry has built-in navigation. Documentation gap. No code change needed; evidence = current screens. | E11: Already in build | F11: #881
A12: autosave | B12: Clarify whether the app autosaves on connectivity loss/interruption/closure, and data-recovery mechanisms. | C12: Platform behavior / UX | D12: Already implemented in the current build — CSEntry partial-save. Document. No code change needed; evidence = current screens. | E12: Already in build | F12: #882
A13: resume | B13: Clarify whether the system can detect incomplete interviews and resume from the last saved point. | C13: Platform behavior / UX | D13: Already implemented in the current build — Partial-save resume. Document. No code change needed; evidence = current screens. | E13: Already in build | F13: #883
A14: timeout | B14: Indicate whether sessions time out; if so, how unsaved responses are handled and whether enumerators are notified. | C14: Platform behavior / UX | D14: Working as designed — Document behaviour. | E14: By design | F14: #884
... A91: Q199 | B91: XJ flags that all questions with an 'Other (specify)' option lack the 'specify' data field; Q199 is on that list. Ensure the 'Other' option exposes a free-text capture. | C91: Data capture — Other (specify) field | D91: VERIFIED in current build (2026-08 audit of the live F4 dictionary) — free-text capture present as Q199_WTP_OTHER_TXT. | E91: Verified in build | F91: #999
